Parameterized_modules/Exp_sum/exp_sum.v
module exp_sum
(
        input  wire [7:0] exp_A, 
        input  wire [7:0] exp_B,
        output wire [9:0] exp_res
);



assign exp_res = exp_A + exp_B - 127;
 

endmodule

Parameterized_modules/Exp_sum/testbench.v
`timescale 1ns/1ps


module testbench;

reg [7:0] exp_A;
reg [7:0] exp_B;



exp_sum DUT (
        .exp_A(exp_A),
        .exp_B(exp_B)
);

initial
begin
        $dumpfile("out.vcd");
        $dumpvars(0, testbench);


        exp_A = 8'b0011_1110;
        exp_B = 8'b0100_0010;  //-61
        
        #2;

        exp_A = 8'b0011_1110;
        exp_B = 8'b0100_0001;  //-62
        
        #2;
        exp_A = 8'b0011_1110;  //-65
        exp_B = 8'b0100_0000;  //-63
        
        #2;

        exp_A = 8'b0011_1110;
        exp_B = 8'b0011_1111;  //-64
        
        #2;

        exp_A = 8'b0011_1110;  //-65
        exp_B = 8'b0010_1010;  //-85
        
        #2;

        exp_A = 8'b0011_1110;  //-65
        exp_B = 8'b0010_1001;  //-86
        
        #2;

        exp_A = 8'b1111_1110;  //127
        exp_B = 8'b1000_0000;  //1
        
        #2;

        exp_A = 8'b1111_1110;  //127
        exp_B = 8'b1111_1110;  //127
        
        #2;

        exp_A = 8'b1100_0010;  //67
        exp_B = 8'b1011_1011;  //60
        
        #2;

        exp_A = 8'b1111_1111;  //inf
        exp_B = 8'b1111_1111;  //inf
        
        #2;

        exp_A = 8'b1111_1101;  //127
        exp_B = 8'b0000_0001;  //-126
        
        #2;
        $finish;
end

endmodule

Parameterized_modules/Exp_sum/out.vcd
$date
	Sun Aug 11 11:21:09 2024
$end
$version
	Icarus Verilog
$end
$timescale
	1ps
$end
$scope module testbench $end
$var reg 8 ! exp_A [7:0] $end
$var reg 8 " exp_B [7:0] $end
$scope module DUT $end
$var wire 8 # exp_A [7:0] $end
$var wire 8 $ exp_B [7:0] $end
$var wire 10 % exp_res [9:0] $end
$upscope $end
$upscope $end
$enddefinitions $end
#0
$dumpvars
b1 %
b1000010 $
b111110 #
b1000010 "
b111110 !
$end
#2000
b0 %
b1000001 "
b1000001 $
#4000
b1111111111 %
b1000000 "
b1000000 $
#6000
b1111111110 %
b111111 "
b111111 $
#8000
b1111101001 %
b101010 "
b101010 $
#10000
b1111101000 %
b101001 "
b101001 $
#12000
b10000000 "
b10000000 $
b11111111 %
b11111110 !
b11111110 #
#14000
b101111101 %
b11111110 "
b11111110 $
#16000
b10111011 "
b10111011 $
b11111110 %
b11000010 !
b11000010 #
#18000
b11111111 "
b11111111 $
b101111111 %
b11111111 !
b11111111 #
#20000
b1 "
b1 $
b1111111 %
b11111101 !
b11111101 #
