Parameterized_modules/Normalization_module/normalization_module.v
module normalization_module
#(
        parameter DATA_W = 8
)
(
        input  wire [DATA_W - 1 : 0] vector,
        output wire [DATA_W - 1 : 0] out
);


wire [$clog2(DATA_W): 0] counter [DATA_W - 1 : 0];

genvar i;
generate for (i = 0; i < DATA_W; i = i + 1)
begin: loop
        if (i == 0) begin
                assign counter[i] = (vector[DATA_W - 1] == 1) ? 0 : DATA_W;
        end
        else begin
                assign counter[i] = ((counter[i - 1] == DATA_W) && (vector[DATA_W - 1 - i] == 1)) ? i : counter[i - 1]; 
        end
end
endgenerate

assign out = vector << counter[DATA_W - 1];

endmodule

Parameterized_modules/Normalization_module/testbench.v
`timescale 1ns/1ps

module testbench;
reg [7:0] vector;
wire [7:0] out;

normalization_module #(.DATA_W(8)) DUT (
        .vector(vector),
        .out(out)
 );

initial begin
        $dumpfile("out.vcd");
        $dumpvars(0, testbench);
        vector = 8'b10000000;
        #2;
        vector = 8'b00001100;
        #2;
        vector = 8'b0100000;
        #2;
        vector = 8'b00100000;
        #2;
        vector = 8'b00010000;
        #2;
        vector = 8'b00001000;
        #2;
        vector = 8'b00000100;
        #2;
        vector = 8'b00000010;
        #2;
        vector = 8'b00000001;
        #2;
        vector = 8'b11111111;
        #2;
        vector = 8'b11000011;
        #2;
        vector = 8'b01111000;
        #2;

        $finish;
end
endmodule

Parameterized_modules/Normalization_module/out.vcd
$date
	Sun Jul 28 11:32:01 2024
$end
$version
	Icarus Verilog
$end
$timescale
	1ps
$end
$scope module testbench $end
$var wire 8 ! out [7:0] $end
$var reg 8 " vector [7:0] $end
$scope module DUT $end
$var wire 8 # vector [7:0] $end
$var wire 8 $ out [7:0] $end
$scope begin loop[0] $end
$scope begin genblk2 $end
$upscope $end
$upscope $end
$scope begin loop[1] $end
$scope begin genblk3 $end
$upscope $end
$upscope $end
$scope begin loop[2] $end
$scope begin genblk3 $end
$upscope $end
$upscope $end
$scope begin loop[3] $end
$scope begin genblk3 $end
$upscope $end
$upscope $end
$scope begin loop[4] $end
$scope begin genblk3 $end
$upscope $end
$upscope $end
$scope begin loop[5] $end
$scope begin genblk3 $end
$upscope $end
$upscope $end
$scope begin loop[6] $end
$scope begin genblk3 $end
$upscope $end
$upscope $end
$scope begin loop[7] $end
$scope begin genblk3 $end
$upscope $end
$upscope $end
$upscope $end
$upscope $end
$enddefinitions $end
#0
$dumpvars
b10000000 $
b10000000 #
b10000000 "
b10000000 !
$end
#2000
b11000000 !
b11000000 $
b1100 "
b1100 #
#4000
b10000000 !
b10000000 $
b100000 "
b100000 #
#8000
b10000000 !
b10000000 $
b10000 "
b10000 #
#10000
b10000000 !
b10000000 $
b1000 "
b1000 #
#12000
b10000000 !
b10000000 $
b100 "
b100 #
#14000
b10000000 !
b10000000 $
b10 "
b10 #
#16000
b10000000 !
b10000000 $
b1 "
b1 #
#18000
b11111111 !
b11111111 $
b11111111 "
b11111111 #
#20000
b11000011 !
b11000011 $
b11000011 "
b11000011 #
#22000
b11110000 !
b11110000 $
b1111000 "
b1111000 #
