Parameterized_modules/clk_div/clk_div.v
module clk_div
#(
        parameter DIV = 2
)
(
        input  wire clk,
        input  wire reset,
        output wor  clk_div
);
reg [$clog2(DIV) - 1:0] counter;




always @(posedge clk) begin
        if (reset) begin
                counter <= 0;
                
        end
        else begin
                if (counter == DIV - 1) begin
                        counter <= 0;
                end
                else counter <= counter + 1;
                
        end
end

genvar g;

generate for (g = 0; g < DIV / 2; g = g + 1)
begin: loop_1
assign clk_div = (counter == g) ? 1 : 0;
end     
endgenerate

endmodule

Parameterized_modules/clk_div/testbench.v
`timescale 1ns/1ps


module testbench;
reg clk;
reg reset;



initial begin
        clk = 0;
        reset = 0;
end
always #1 clk = ~clk;


clk_div #(.DIV(6)) DUT (
        .clk(clk),
        .reset(reset)
        
);





initial begin
        $dumpfile("out.vcd");
        $dumpvars(0, testbench);
        #12;
        reset = 1;
        #2;
        reset = 0;

        #1000;

        $finish;
end






endmodule

Parameterized_modules/clk_div/out.vcd
$date
	Sun Jul 14 19:03:23 2024
$end
$version
	Icarus Verilog
$end
$timescale
	1ps
$end
$scope module testbench $end
$var reg 1 ! clk $end
$var reg 1 " reset $end
$scope module DUT $end
$var wire 1 ! clk $end
$var wire 1 # clk_div $end
$var wire 1 " reset $end
$var reg 3 $ counter [2:0] $end
$scope begin loop_1[0] $end
$upscope $end
$scope begin loop_1[1] $end
$upscope $end
$scope begin loop_1[2] $end
$upscope $end
$upscope $end
$upscope $end
$enddefinitions $end
#0
$dumpvars
bx $
x#
0"
0!
$end
#1000
1!
#2000
0!
#3000
1!
#4000
0!
#5000
1!
#6000
0!
#7000
1!
#8000
0!
#9000
1!
#10000
0!
#11000
1!
#12000
0!
1"
#13000
1#
b0 $
1!
#14000
0!
0"
#15000
b1 $
1!
#16000
0!
#17000
b10 $
1!
#18000
0!
#19000
0#
b11 $
1!
#20000
0!
#21000
b100 $
1!
#22000
0!
#23000
b101 $
1!
#24000
0!
#25000
1#
b0 $
1!
#26000
0!
#27000
b1 $
1!
#28000
0!
#29000
b10 $
1!
#30000
0!
#31000
0#
b11 $
1!
#32000
0!
#33000
b100 $
1!
#34000
0!
#35000
b101 $
1!
#36000
0!
#37000
1#
b0 $
1!
#38000
0!
#39000
b1 $
1!
#40000
0!
#41000
b10 $
1!
#42000
0!
#43000
0#
b11 $
1!
#44000
0!
#45000
b100 $
1!
#46000
0!
#47000
b101 $
1!
#48000
0!
#49000
1#
b0 $
1!
#50000
0!
#51000
b1 $
1!
#52000
0!
#53000
b10 $
1!
#54000
0!
#55000
0#
b11 $
1!
#56000
0!
#57000
b100 $
1!
#58000
0!
#59000
b101 $
1!
#60000
0!
#61000
1#
b0 $
1!
#62000
0!
#63000
b1 $
1!
#64000
0!
#65000
b10 $
1!
#66000
0!
#67000
0#
b11 $
1!
#68000
0!
#69000
b100 $
1!
#70000
0!
#71000
b101 $
1!
#72000
0!
#73000
1#
b0 $
1!
#74000
0!
#75000
b1 $
1!
#76000
0!
#77000
b10 $
1!
#78000
0!
#79000
0#
b11 $
1!
#80000
0!
#81000
b100 $
1!
#82000
0!
#83000
b101 $
1!
#84000
0!
#85000
1#
b0 $
1!
#86000
0!
#87000
b1 $
1!
#88000
0!
#89000
b10 $
1!
#90000
0!
#91000
0#
b11 $
1!
#92000
0!
#93000
b100 $
1!
#94000
0!
#95000
b101 $
1!
#96000
0!
#97000
1#
b0 $
1!
#98000
0!
#99000
b1 $
1!
#100000
0!
#101000
b10 $
1!
#102000
0!
#103000
0#
b11 $
1!
#104000
0!
#105000
b100 $
1!
#106000
0!
#107000
b101 $
1!
#108000
0!
#109000
1#
b0 $
1!
#110000
0!
#111000
b1 $
1!
#112000
0!
#113000
b10 $
1!
#114000
0!
#115000
0#
b11 $
1!
#116000
0!
#117000
b100 $
1!
#118000
0!
#119000
b101 $
1!
#120000
0!
#121000
1#
b0 $
1!
#122000
0!
#123000
b1 $
1!
#124000
0!
#125000
b10 $
1!
#126000
0!
#127000
0#
b11 $
1!
#128000
0!
#129000
b100 $
1!
#130000
0!
#131000
b101 $
1!
#132000
0!
#133000
1#
b0 $
1!
#134000
0!
#135000
b1 $
1!
#136000
0!
#137000
b10 $
1!
#138000
0!
#139000
0#
b11 $
1!
#140000
0!
#141000
b100 $
1!
#142000
0!
#143000
b101 $
1!
#144000
0!
#145000
1#
b0 $
1!
#146000
0!
#147000
b1 $
1!
#148000
0!
#149000
b10 $
1!
#150000
0!
#151000
0#
b11 $
1!
#152000
0!
#153000
b100 $
1!
#154000
0!
#155000
b101 $
1!
#156000
0!
#157000
1#
b0 $
1!
#158000
0!
#159000
b1 $
1!
#160000
0!
#161000
b10 $
1!
#162000
0!
#163000
0#
b11 $
1!
#164000
0!
#165000
b100 $
1!
#166000
0!
#167000
b101 $
1!
#168000
0!
#169000
1#
b0 $
1!
#170000
0!
#171000
b1 $
1!
#172000
0!
#173000
b10 $
1!
#174000
0!
#175000
0#
b11 $
1!
#176000
0!
#177000
b100 $
1!
#178000
0!
#179000
b101 $
1!
#180000
0!
#181000
1#
b0 $
1!
#182000
0!
#183000
b1 $
1!
#184000
0!
#185000
b10 $
1!
#186000
0!
#187000
0#
b11 $
1!
#188000
0!
#189000
b100 $
1!
#190000
0!
#191000
b101 $
1!
#192000
0!
#193000
1#
b0 $
1!
#194000
0!
#195000
b1 $
1!
#196000
0!
#197000
b10 $
1!
#198000
0!
#199000
0#
b11 $
1!
#200000
0!
#201000
b100 $
1!
#202000
0!
#203000
b101 $
1!
#204000
0!
#205000
1#
b0 $
1!
#206000
0!
#207000
b1 $
1!
#208000
0!
#209000
b10 $
1!
#210000
0!
#211000
0#
b11 $
1!
#212000
0!
#213000
b100 $
1!
#214000
0!
#215000
b101 $
1!
#216000
0!
#217000
1#
b0 $
1!
#218000
0!
#219000
b1 $
1!
#220000
0!
#221000
b10 $
1!
#222000
0!
#223000
0#
b11 $
1!
#224000
0!
#225000
b100 $
1!
#226000
0!
#227000
b101 $
1!
#228000
0!
#229000
1#
b0 $
1!
#230000
0!
#231000
b1 $
1!
#232000
0!
#233000
b10 $
1!
#234000
0!
#235000
0#
b11 $
1!
#236000
0!
#237000
b100 $
1!
#238000
0!
#239000
b101 $
1!
#240000
0!
#241000
1#
b0 $
1!
#242000
0!
#243000
b1 $
1!
#244000
0!
#245000
b10 $
1!
#246000
0!
#247000
0#
b11 $
1!
#248000
0!
#249000
b100 $
1!
#250000
0!
#251000
b101 $
1!
#252000
0!
#253000
1#
b0 $
1!
#254000
0!
#255000
b1 $
1!
#256000
0!
#257000
b10 $
1!
#258000
0!
#259000
0#
b11 $
1!
#260000
0!
#261000
b100 $
1!
#262000
0!
#263000
b101 $
1!
#264000
0!
#265000
1#
b0 $
1!
#266000
0!
#267000
b1 $
1!
#268000
0!
#269000
b10 $
1!
#270000
0!
#271000
0#
b11 $
1!
#272000
0!
#273000
b100 $
1!
#274000
0!
#275000
b101 $
1!
#276000
0!
#277000
1#
b0 $
1!
#278000
0!
#279000
b1 $
1!
#280000
0!
#281000
b10 $
1!
#282000
0!
#283000
0#
b11 $
1!
#284000
0!
#285000
b100 $
1!
#286000
0!
#287000
b101 $
1!
#288000
0!
#289000
1#
b0 $
1!
#290000
0!
#291000
b1 $
1!
#292000
0!
#293000
b10 $
1!
#294000
0!
#295000
0#
b11 $
1!
#296000
0!
#297000
b100 $
1!
#298000
0!
#299000
b101 $
1!
#300000
0!
#301000
1#
b0 $
1!
#302000
0!
#303000
b1 $
1!
#304000
0!
#305000
b10 $
1!
#306000
0!
#307000
0#
b11 $
1!
#308000
0!
#309000
b100 $
1!
#310000
0!
#311000
b101 $
1!
#312000
0!
#313000
1#
b0 $
1!
#314000
0!
#315000
b1 $
1!
#316000
0!
#317000
b10 $
1!
#318000
0!
#319000
0#
b11 $
1!
#320000
0!
#321000
b100 $
1!
#322000
0!
#323000
b101 $
1!
#324000
0!
#325000
1#
b0 $
1!
#326000
0!
#327000
b1 $
1!
#328000
0!
#329000
b10 $
1!
#330000
0!
#331000
0#
b11 $
1!
#332000
0!
#333000
b100 $
1!
#334000
0!
#335000
b101 $
1!
#336000
0!
#337000
1#
b0 $
1!
#338000
0!
#339000
b1 $
1!
#340000
0!
#341000
b10 $
1!
#342000
0!
#343000
0#
b11 $
1!
#344000
0!
#345000
b100 $
1!
#346000
0!
#347000
b101 $
1!
#348000
0!
#349000
1#
b0 $
1!
#350000
0!
#351000
b1 $
1!
#352000
0!
#353000
b10 $
1!
#354000
0!
#355000
0#
b11 $
1!
#356000
0!
#357000
b100 $
1!
#358000
0!
#359000
b101 $
1!
#360000
0!
#361000
1#
b0 $
1!
#362000
0!
#363000
b1 $
1!
#364000
0!
#365000
b10 $
1!
#366000
0!
#367000
0#
b11 $
1!
#368000
0!
#369000
b100 $
1!
#370000
0!
#371000
b101 $
1!
#372000
0!
#373000
1#
b0 $
1!
#374000
0!
#375000
b1 $
1!
#376000
0!
#377000
b10 $
1!
#378000
0!
#379000
0#
b11 $
1!
#380000
0!
#381000
b100 $
1!
#382000
0!
#383000
b101 $
1!
#384000
0!
#385000
1#
b0 $
1!
#386000
0!
#387000
b1 $
1!
#388000
0!
#389000
b10 $
1!
#390000
0!
#391000
0#
b11 $
1!
#392000
0!
#393000
b100 $
1!
#394000
0!
#395000
b101 $
1!
#396000
0!
#397000
1#
b0 $
1!
#398000
0!
#399000
b1 $
1!
#400000
0!
#401000
b10 $
1!
#402000
0!
#403000
0#
b11 $
1!
#404000
0!
#405000
b100 $
1!
#406000
0!
#407000
b101 $
1!
#408000
0!
#409000
1#
b0 $
1!
#410000
0!
#411000
b1 $
1!
#412000
0!
#413000
b10 $
1!
#414000
0!
#415000
0#
b11 $
1!
#416000
0!
#417000
b100 $
1!
#418000
0!
#419000
b101 $
1!
#420000
0!
#421000
1#
b0 $
1!
#422000
0!
#423000
b1 $
1!
#424000
0!
#425000
b10 $
1!
#426000
0!
#427000
0#
b11 $
1!
#428000
0!
#429000
b100 $
1!
#430000
0!
#431000
b101 $
1!
#432000
0!
#433000
1#
b0 $
1!
#434000
0!
#435000
b1 $
1!
#436000
0!
#437000
b10 $
1!
#438000
0!
#439000
0#
b11 $
1!
#440000
0!
#441000
b100 $
1!
#442000
0!
#443000
b101 $
1!
#444000
0!
#445000
1#
b0 $
1!
#446000
0!
#447000
b1 $
1!
#448000
0!
#449000
b10 $
1!
#450000
0!
#451000
0#
b11 $
1!
#452000
0!
#453000
b100 $
1!
#454000
0!
#455000
b101 $
1!
#456000
0!
#457000
1#
b0 $
1!
#458000
0!
#459000
b1 $
1!
#460000
0!
#461000
b10 $
1!
#462000
0!
#463000
0#
b11 $
1!
#464000
0!
#465000
b100 $
1!
#466000
0!
#467000
b101 $
1!
#468000
0!
#469000
1#
b0 $
1!
#470000
0!
#471000
b1 $
1!
#472000
0!
#473000
b10 $
1!
#474000
0!
#475000
0#
b11 $
1!
#476000
0!
#477000
b100 $
1!
#478000
0!
#479000
b101 $
1!
#480000
0!
#481000
1#
b0 $
1!
#482000
0!
#483000
b1 $
1!
#484000
0!
#485000
b10 $
1!
#486000
0!
#487000
0#
b11 $
1!
#488000
0!
#489000
b100 $
1!
#490000
0!
#491000
b101 $
1!
#492000
0!
#493000
1#
b0 $
1!
#494000
0!
#495000
b1 $
1!
#496000
0!
#497000
b10 $
1!
#498000
0!
#499000
0#
b11 $
1!
#500000
0!
#501000
b100 $
1!
#502000
0!
#503000
b101 $
1!
#504000
0!
#505000
1#
b0 $
1!
#506000
0!
#507000
b1 $
1!
#508000
0!
#509000
b10 $
1!
#510000
0!
#511000
0#
b11 $
1!
#512000
0!
#513000
b100 $
1!
#514000
0!
#515000
b101 $
1!
#516000
0!
#517000
1#
b0 $
1!
#518000
0!
#519000
b1 $
1!
#520000
0!
#521000
b10 $
1!
#522000
0!
#523000
0#
b11 $
1!
#524000
0!
#525000
b100 $
1!
#526000
0!
#527000
b101 $
1!
#528000
0!
#529000
1#
b0 $
1!
#530000
0!
#531000
b1 $
1!
#532000
0!
#533000
b10 $
1!
#534000
0!
#535000
0#
b11 $
1!
#536000
0!
#537000
b100 $
1!
#538000
0!
#539000
b101 $
1!
#540000
0!
#541000
1#
b0 $
1!
#542000
0!
#543000
b1 $
1!
#544000
0!
#545000
b10 $
1!
#546000
0!
#547000
0#
b11 $
1!
#548000
0!
#549000
b100 $
1!
#550000
0!
#551000
b101 $
1!
#552000
0!
#553000
1#
b0 $
1!
#554000
0!
#555000
b1 $
1!
#556000
0!
#557000
b10 $
1!
#558000
0!
#559000
0#
b11 $
1!
#560000
0!
#561000
b100 $
1!
#562000
0!
#563000
b101 $
1!
#564000
0!
#565000
1#
b0 $
1!
#566000
0!
#567000
b1 $
1!
#568000
0!
#569000
b10 $
1!
#570000
0!
#571000
0#
b11 $
1!
#572000
0!
#573000
b100 $
1!
#574000
0!
#575000
b101 $
1!
#576000
0!
#577000
1#
b0 $
1!
#578000
0!
#579000
b1 $
1!
#580000
0!
#581000
b10 $
1!
#582000
0!
#583000
0#
b11 $
1!
#584000
0!
#585000
b100 $
1!
#586000
0!
#587000
b101 $
1!
#588000
0!
#589000
1#
b0 $
1!
#590000
0!
#591000
b1 $
1!
#592000
0!
#593000
b10 $
1!
#594000
0!
#595000
0#
b11 $
1!
#596000
0!
#597000
b100 $
1!
#598000
0!
#599000
b101 $
1!
#600000
0!
#601000
1#
b0 $
1!
#602000
0!
#603000
b1 $
1!
#604000
0!
#605000
b10 $
1!
#606000
0!
#607000
0#
b11 $
1!
#608000
0!
#609000
b100 $
1!
#610000
0!
#611000
b101 $
1!
#612000
0!
#613000
1#
b0 $
1!
#614000
0!
#615000
b1 $
1!
#616000
0!
#617000
b10 $
1!
#618000
0!
#619000
0#
b11 $
1!
#620000
0!
#621000
b100 $
1!
#622000
0!
#623000
b101 $
1!
#624000
0!
#625000
1#
b0 $
1!
#626000
0!
#627000
b1 $
1!
#628000
0!
#629000
b10 $
1!
#630000
0!
#631000
0#
b11 $
1!
#632000
0!
#633000
b100 $
1!
#634000
0!
#635000
b101 $
1!
#636000
0!
#637000
1#
b0 $
1!
#638000
0!
#639000
b1 $
1!
#640000
0!
#641000
b10 $
1!
#642000
0!
#643000
0#
b11 $
1!
#644000
0!
#645000
b100 $
1!
#646000
0!
#647000
b101 $
1!
#648000
0!
#649000
1#
b0 $
1!
#650000
0!
#651000
b1 $
1!
#652000
0!
#653000
b10 $
1!
#654000
0!
#655000
0#
b11 $
1!
#656000
0!
#657000
b100 $
1!
#658000
0!
#659000
b101 $
1!
#660000
0!
#661000
1#
b0 $
1!
#662000
0!
#663000
b1 $
1!
#664000
0!
#665000
b10 $
1!
#666000
0!
#667000
0#
b11 $
1!
#668000
0!
#669000
b100 $
1!
#670000
0!
#671000
b101 $
1!
#672000
0!
#673000
1#
b0 $
1!
#674000
0!
#675000
b1 $
1!
#676000
0!
#677000
b10 $
1!
#678000
0!
#679000
0#
b11 $
1!
#680000
0!
#681000
b100 $
1!
#682000
0!
#683000
b101 $
1!
#684000
0!
#685000
1#
b0 $
1!
#686000
0!
#687000
b1 $
1!
#688000
0!
#689000
b10 $
1!
#690000
0!
#691000
0#
b11 $
1!
#692000
0!
#693000
b100 $
1!
#694000
0!
#695000
b101 $
1!
#696000
0!
#697000
1#
b0 $
1!
#698000
0!
#699000
b1 $
1!
#700000
0!
#701000
b10 $
1!
#702000
0!
#703000
0#
b11 $
1!
#704000
0!
#705000
b100 $
1!
#706000
0!
#707000
b101 $
1!
#708000
0!
#709000
1#
b0 $
1!
#710000
0!
#711000
b1 $
1!
#712000
0!
#713000
b10 $
1!
#714000
0!
#715000
0#
b11 $
1!
#716000
0!
#717000
b100 $
1!
#718000
0!
#719000
b101 $
1!
#720000
0!
#721000
1#
b0 $
1!
#722000
0!
#723000
b1 $
1!
#724000
0!
#725000
b10 $
1!
#726000
0!
#727000
0#
b11 $
1!
#728000
0!
#729000
b100 $
1!
#730000
0!
#731000
b101 $
1!
#732000
0!
#733000
1#
b0 $
1!
#734000
0!
#735000
b1 $
1!
#736000
0!
#737000
b10 $
1!
#738000
0!
#739000
0#
b11 $
1!
#740000
0!
#741000
b100 $
1!
#742000
0!
#743000
b101 $
1!
#744000
0!
#745000
1#
b0 $
1!
#746000
0!
#747000
b1 $
1!
#748000
0!
#749000
b10 $
1!
#750000
0!
#751000
0#
b11 $
1!
#752000
0!
#753000
b100 $
1!
#754000
0!
#755000
b101 $
1!
#756000
0!
#757000
1#
b0 $
1!
#758000
0!
#759000
b1 $
1!
#760000
0!
#761000
b10 $
1!
#762000
0!
#763000
0#
b11 $
1!
#764000
0!
#765000
b100 $
1!
#766000
0!
#767000
b101 $
1!
#768000
0!
#769000
1#
b0 $
1!
#770000
0!
#771000
b1 $
1!
#772000
0!
#773000
b10 $
1!
#774000
0!
#775000
0#
b11 $
1!
#776000
0!
#777000
b100 $
1!
#778000
0!
#779000
b101 $
1!
#780000
0!
#781000
1#
b0 $
1!
#782000
0!
#783000
b1 $
1!
#784000
0!
#785000
b10 $
1!
#786000
0!
#787000
0#
b11 $
1!
#788000
0!
#789000
b100 $
1!
#790000
0!
#791000
b101 $
1!
#792000
0!
#793000
1#
b0 $
1!
#794000
0!
#795000
b1 $
1!
#796000
0!
#797000
b10 $
1!
#798000
0!
#799000
0#
b11 $
1!
#800000
0!
#801000
b100 $
1!
#802000
0!
#803000
b101 $
1!
#804000
0!
#805000
1#
b0 $
1!
#806000
0!
#807000
b1 $
1!
#808000
0!
#809000
b10 $
1!
#810000
0!
#811000
0#
b11 $
1!
#812000
0!
#813000
b100 $
1!
#814000
0!
#815000
b101 $
1!
#816000
0!
#817000
1#
b0 $
1!
#818000
0!
#819000
b1 $
1!
#820000
0!
#821000
b10 $
1!
#822000
0!
#823000
0#
b11 $
1!
#824000
0!
#825000
b100 $
1!
#826000
0!
#827000
b101 $
1!
#828000
0!
#829000
1#
b0 $
1!
#830000
0!
#831000
b1 $
1!
#832000
0!
#833000
b10 $
1!
#834000
0!
#835000
0#
b11 $
1!
#836000
0!
#837000
b100 $
1!
#838000
0!
#839000
b101 $
1!
#840000
0!
#841000
1#
b0 $
1!
#842000
0!
#843000
b1 $
1!
#844000
0!
#845000
b10 $
1!
#846000
0!
#847000
0#
b11 $
1!
#848000
0!
#849000
b100 $
1!
#850000
0!
#851000
b101 $
1!
#852000
0!
#853000
1#
b0 $
1!
#854000
0!
#855000
b1 $
1!
#856000
0!
#857000
b10 $
1!
#858000
0!
#859000
0#
b11 $
1!
#860000
0!
#861000
b100 $
1!
#862000
0!
#863000
b101 $
1!
#864000
0!
#865000
1#
b0 $
1!
#866000
0!
#867000
b1 $
1!
#868000
0!
#869000
b10 $
1!
#870000
0!
#871000
0#
b11 $
1!
#872000
0!
#873000
b100 $
1!
#874000
0!
#875000
b101 $
1!
#876000
0!
#877000
1#
b0 $
1!
#878000
0!
#879000
b1 $
1!
#880000
0!
#881000
b10 $
1!
#882000
0!
#883000
0#
b11 $
1!
#884000
0!
#885000
b100 $
1!
#886000
0!
#887000
b101 $
1!
#888000
0!
#889000
1#
b0 $
1!
#890000
0!
#891000
b1 $
1!
#892000
0!
#893000
b10 $
1!
#894000
0!
#895000
0#
b11 $
1!
#896000
0!
#897000
b100 $
1!
#898000
0!
#899000
b101 $
1!
#900000
0!
#901000
1#
b0 $
1!
#902000
0!
#903000
b1 $
1!
#904000
0!
#905000
b10 $
1!
#906000
0!
#907000
0#
b11 $
1!
#908000
0!
#909000
b100 $
1!
#910000
0!
#911000
b101 $
1!
#912000
0!
#913000
1#
b0 $
1!
#914000
0!
#915000
b1 $
1!
#916000
0!
#917000
b10 $
1!
#918000
0!
#919000
0#
b11 $
1!
#920000
0!
#921000
b100 $
1!
#922000
0!
#923000
b101 $
1!
#924000
0!
#925000
1#
b0 $
1!
#926000
0!
#927000
b1 $
1!
#928000
0!
#929000
b10 $
1!
#930000
0!
#931000
0#
b11 $
1!
#932000
0!
#933000
b100 $
1!
#934000
0!
#935000
b101 $
1!
#936000
0!
#937000
1#
b0 $
1!
#938000
0!
#939000
b1 $
1!
#940000
0!
#941000
b10 $
1!
#942000
0!
#943000
0#
b11 $
1!
#944000
0!
#945000
b100 $
1!
#946000
0!
#947000
b101 $
1!
#948000
0!
#949000
1#
b0 $
1!
#950000
0!
#951000
b1 $
1!
#952000
0!
#953000
b10 $
1!
#954000
0!
#955000
0#
b11 $
1!
#956000
0!
#957000
b100 $
1!
#958000
0!
#959000
b101 $
1!
#960000
0!
#961000
1#
b0 $
1!
#962000
0!
#963000
b1 $
1!
#964000
0!
#965000
b10 $
1!
#966000
0!
#967000
0#
b11 $
1!
#968000
0!
#969000
b100 $
1!
#970000
0!
#971000
b101 $
1!
#972000
0!
#973000
1#
b0 $
1!
#974000
0!
#975000
b1 $
1!
#976000
0!
#977000
b10 $
1!
#978000
0!
#979000
0#
b11 $
1!
#980000
0!
#981000
b100 $
1!
#982000
0!
#983000
b101 $
1!
#984000
0!
#985000
1#
b0 $
1!
#986000
0!
#987000
b1 $
1!
#988000
0!
#989000
b10 $
1!
#990000
0!
#991000
0#
b11 $
1!
#992000
0!
#993000
b100 $
1!
#994000
0!
#995000
b101 $
1!
#996000
0!
#997000
1#
b0 $
1!
#998000
0!
#999000
b1 $
1!
#1000000
0!
#1001000
b10 $
1!
#1002000
0!
#1003000
0#
b11 $
1!
#1004000
0!
#1005000
b100 $
1!
#1006000
0!
#1007000
b101 $
1!
#1008000
0!
#1009000
1#
b0 $
1!
#1010000
0!
#1011000
b1 $
1!
#1012000
0!
#1013000
b10 $
1!
