Parameterized_modules/LIFO_buffer/LIFO_buffer.v
module LIFO_buffer
#(      parameter LIFO_SIZE = 8, 
        parameter DATA_W    = 8
)
(
        input  wire clk,
        input  wire reset,
        input  wire write,
        input  wire read,
        input  wire [DATA_W - 1:0] data_in,
        output reg  [DATA_W - 1:0] data_out,
        output reg  val,
        output reg  full
);

reg [LIFO_SIZE      -1:0] buffer [DATA_W - 1:0];
reg [$clog2(LIFO_SIZE):0] buffer_level;
integer i;



always @ (posedge clk or posedge reset) begin
        if (reset) begin
                for (i = 0; i < LIFO_SIZE; i = i + 1) begin
                        buffer[i] <= 0;
                end
                buffer_level <= 0;
                full <= 0;
                val <= 1;
        end
        else if (read & !full & !write) begin
                if (buffer_level == 0)  begin
                        val <= 0;
                        end
                else begin
                        buffer_level <= buffer_level - 1;
                        data_out <= buffer[buffer_level - 1];
                end
        end
        else if (write & !full & !read) begin
                val <= 1;
                buffer[buffer_level] <= data_in;
                buffer_level <= buffer_level + 1;
                if (buffer_level + 1 == LIFO_SIZE) begin
                        full <= 1;
                        val <= 0;
                end
        end
        else if (write & read & !full) begin
                val <= 1;
                data_out <= data_in;
        end
        else if (read & full & !write) begin
                buffer_level <= buffer_level - 1;
                data_out <= buffer[buffer_level - 1];
                full <= 0;
                val <= 1;
        end
        else if (write & full) begin
                data_out <= data_in;
        end
 
end
endmodule

Parameterized_modules/LIFO_buffer/testbench.v
`timescale 1ns/1ps


module testbench;
reg clk;
reg reset;
reg write;
reg read;
reg [7:0] data_in;

initial begin
        clk = 0;
        reset = 0;
        write = 0;
        read = 0;
end
always #1 clk = ~clk;


LIFO_buffer #(.LIFO_SIZE(8), .DATA_W(8)) DUT (
        .clk(clk),
        .reset(reset),
        .write(write),
        .read(read),
        .data_in(data_in)
        
);





initial begin
        $dumpfile("out.vcd");
        $dumpvars(0, testbench);
        #11;
        reset = 1;
        #2;
        reset = 0;
        #2;
        write = 1;
        data_in = 8'b11111111;
        #2;
        data_in = 8'b00000000;
        #2;
        data_in = 8'b11110000;
        #2;
        data_in = 8'b00001111;
        #2;
        write = 0;
        #5;
        read = 1;
        #2;
        read = 1;
        #2;
        read = 1;
        #2;
        read = 1;
        #2;
        read = 1;
        #2;
        read = 0;
        #2;
        write = 1;
        data_in = 8'b11111111;
        #2;
        data_in = 8'b00000000;
        #2;
        data_in = 8'b11110000;
        #2;
        data_in = 8'b00001111;
        #2;
        data_in = 8'b01010101;
        #2;
        data_in = 8'b01101100;
        #2;
        data_in = 8'b00010000;
        #2;
        read = 1;
        data_in = 8'b00000001;
        #2;
        write = 0;
        read = 0;
        #2;
        write = 1;
        data_in = 8'b10000001;
        #2;
        write = 0;
        #2;
        read = 1;
        #2;
        read = 0;
        #2;
        write = 1;
        data_in = 8'b10000001;
        #2;
        data_in = 8'b10000000;
        #2;
        write = 0;
        reset = 1;
        #2;
        reset = 0;
        



        #1000;

        $finish;
end






endmodule

Parameterized_modules/LIFO_buffer/out.vcd
$date
	Mon Jul 15 15:31:15 2024
$end
$version
	Icarus Verilog
$end
$timescale
	1ps
$end
$scope module testbench $end
$var reg 1 ! clk $end
$var reg 8 " data_in [7:0] $end
$var reg 1 # read $end
$var reg 1 $ reset $end
$var reg 1 % write $end
$scope module DUT $end
$var wire 1 ! clk $end
$var wire 8 & data_in [7:0] $end
$var wire 1 # read $end
$var wire 1 $ reset $end
$var wire 1 % write $end
$var reg 4 ' buffer_level [3:0] $end
$var reg 8 ( data_out [7:0] $end
$var reg 1 ) full $end
$var reg 1 * val $end
$var integer 32 + i [31:0] $end
$upscope $end
$upscope $end
$enddefinitions $end
#0
$dumpvars
bx +
x*
x)
bx (
bx '
bx &
0%
0$
0#
bx "
0!
$end
#1000
1!
#2000
0!
#3000
1!
#4000
0!
#5000
1!
#6000
0!
#7000
1!
#8000
0!
#9000
1!
#10000
0!
#11000
1*
0)
b0 '
b1000 +
1!
1$
#12000
0!
#13000
1!
0$
#14000
0!
#15000
b1 '
1!
b11111111 "
b11111111 &
1%
#16000
0!
#17000
b10 '
1!
b0 "
b0 &
#18000
0!
#19000
b11 '
1!
b11110000 "
b11110000 &
#20000
0!
#21000
b100 '
1!
b1111 "
b1111 &
#22000
0!
#23000
1!
0%
#24000
0!
#25000
1!
#26000
0!
#27000
1!
#28000
0!
1#
#29000
b1111 (
b11 '
1!
#30000
0!
#31000
b11110000 (
b10 '
1!
#32000
0!
#33000
b0 (
b1 '
1!
#34000
0!
#35000
b11111111 (
b0 '
1!
#36000
0!
#37000
0*
1!
#38000
0!
0#
#39000
1!
#40000
0!
b11111111 "
b11111111 &
1%
#41000
b1 '
1*
1!
#42000
0!
b0 "
b0 &
#43000
b10 '
1!
#44000
0!
b11110000 "
b11110000 &
#45000
b11 '
1!
#46000
0!
b1111 "
b1111 &
#47000
b100 '
1!
#48000
0!
b1010101 "
b1010101 &
#49000
b101 '
1!
#50000
0!
b1101100 "
b1101100 &
#51000
b110 '
1!
#52000
0!
b10000 "
b10000 &
#53000
b111 '
1!
#54000
0!
b1 "
b1 &
1#
#55000
b1 (
1!
#56000
0!
0#
0%
#57000
1!
#58000
0!
b10000001 "
b10000001 &
1%
#59000
0*
1)
b1000 '
1!
#60000
0!
0%
#61000
1!
#62000
0!
1#
#63000
1*
0)
b10000001 (
b111 '
1!
#64000
0!
0#
#65000
1!
#66000
0!
1%
#67000
0*
1)
b1000 '
1!
#68000
0!
b10000000 "
b10000000 &
#69000
b10000000 (
1!
#70000
1*
0)
b0 '
b1000 +
0!
1$
0%
#71000
b1000 +
1!
#72000
0!
0$
