Parameterized_modules/Rounding_module/rounding_module.v
`define ROUNDING_SIFT 32
`define MANT_START 10

module rounding_module
#(
        parameter DATA_W = 30
)
(
        input  wire [1          : 0] rouding_mode,
        input  wire [DATA_W - 1 : 0] data,
        output wire [22         : 0] mant
);


wire rounding_bit = data[DATA_W - `ROUNDING_SIFT];
wire sticky_bit   = (DATA_W > `ROUNDING_SIFT) ? | data[DATA_W-1-`ROUNDING_SIFT : 0] : 0;

assign mant =   (rouding_mode == 1                               ) ? data[DATA_W-`MANT_START : DATA_W-`ROUNDING_SIFT]        :  // rounding to 0
                (rouding_mode == 2 && !data[DATA_W - 1]          ) ? data[DATA_W-`MANT_START : DATA_W-`ROUNDING_SIFT] + 1'b1 :  // rounding to +INF(+)
                (rouding_mode == 2 &&  data[DATA_W - 1]          ) ? data[DATA_W-`MANT_START : DATA_W-`ROUNDING_SIFT]        :  // rounding to +INF(-)
                (rouding_mode == 3 &&  data[DATA_W - 1]          ) ? data[DATA_W-`MANT_START : DATA_W-`ROUNDING_SIFT] + 1'b1 :  // rounding to -INF(+)
                (rouding_mode == 3 && !data[DATA_W - 1]          ) ? data[DATA_W-`MANT_START : DATA_W-`ROUNDING_SIFT]        :  // rounding to -INF(-)
                (rouding_mode == 0 &&  rounding_bit && sticky_bit) ? data[DATA_W-`MANT_START : DATA_W-`ROUNDING_SIFT] + 1'b1 :  // rounding to nearest even
                                                                     data[DATA_W-`MANT_START : DATA_W-`ROUNDING_SIFT];


endmodule

Parameterized_modules/Rounding_module/testbench.v
`timescale 1ns/1ps

module testbench;
reg [34:0] vector;
reg [1:0] rouding_mode;

rounding_module #(.DATA_W(35)) DUT (
        .data(vector),
        .rouding_mode(rouding_mode)
 );

initial begin
        $dumpfile("out.vcd");
        $dumpvars(0, testbench);
        rouding_mode = 0;
        #2;
        vector = 35'b0_10000010_00000000000001000000000_010;
        #2;
        vector = 35'b0_10000010_00000000000001000000000_100;
        #2;
        vector = 35'b0_10000010_00000000000001000000000_000;
        #2;
        vector = 35'b0_10000010_00000000000001000000001_010;
        #2;
        vector = 35'b0_10000010_00000000000000000000001_000;
        #2;
        vector = 35'b0_10000010_00000000000000000100101_000;
        #2;
        rouding_mode = 1;
        vector = 35'b0_10000010_00000000000100100000000_111;
        #2;
        vector = 35'b0_10000010_10000000000111111000000_001;
        #2;
        vector = 35'b0_10000010_10000000000000111100000_010;
        #2;
        vector = 35'b0_10000010_10000000000000000000010_100;
        #2;
        vector = 35'b0_10000010_10000000000000000000001_011;
        #2;

        $finish;
end
endmodule

Parameterized_modules/Rounding_module/out.vcd
$date
	Tue Jul 30 14:45:05 2024
$end
$version
	Icarus Verilog
$end
$timescale
	1ps
$end
$scope module testbench $end
$var reg 2 ! rouding_mode [1:0] $end
$var reg 35 " vector [34:0] $end
$scope module DUT $end
$var wire 35 # data [34:0] $end
$var wire 2 $ rouding_mode [1:0] $end
$var wire 1 % sticky_bit $end
$var wire 1 & rounding_bit $end
$var wire 23 ' mant [22:0] $end
$upscope $end
$upscope $end
$enddefinitions $end
#0
$dumpvars
bx '
x&
x%
b0 $
bx #
bx "
b0 !
$end
#2000
b1000000000 '
0&
1%
b1000001000000000000001000000000010 "
b1000001000000000000001000000000010 #
#4000
b1000001000000000000001000000000100 "
b1000001000000000000001000000000100 #
#6000
0%
b1000001000000000000001000000000000 "
b1000001000000000000001000000000000 #
#8000
b1000000010 '
1&
1%
b1000001000000000000001000000001010 "
b1000001000000000000001000000001010 #
#10000
b1 '
0%
b1000001000000000000000000000001000 "
b1000001000000000000000000000001000 #
#12000
b100101 '
b1000001000000000000000000100101000 "
b1000001000000000000000000100101000 #
#14000
b100100000000 '
0&
1%
b1000001000000000000100100000000111 "
b1000001000000000000100100000000111 #
b1 !
b1 $
#16000
b10000000000111111000000 '
b1000001010000000000111111000000001 "
b1000001010000000000111111000000001 #
#18000
b10000000000000111100000 '
b1000001010000000000000111100000010 "
b1000001010000000000000111100000010 #
#20000
b10000000000000000000010 '
b1000001010000000000000000000010100 "
b1000001010000000000000000000010100 #
#22000
b10000000000000000000001 '
1&
b1000001010000000000000000000001011 "
b1000001010000000000000000000001011 #
