is_div_3/is_div_3.v
module is_div_3(
        input  wire [7:0] digit,
        output wire OUT
);

assign OUT =    ({digit[7]^digit[6], digit[5]^digit[4], digit[3]^digit[2], digit[1]^digit[0]} == 4'b0000) ? 1'b1 :
                ({digit[7]^digit[6], digit[5]^digit[4], digit[3]^digit[2], digit[1]^digit[0]} == 4'b0011) ? 1'b1 :
                ({digit[7]^digit[6], digit[5]^digit[4], digit[3]^digit[2], digit[1]^digit[0]} == 4'b0101) ? 1'b1 :
                ({digit[7]^digit[6], digit[5]^digit[4], digit[3]^digit[2], digit[1]^digit[0]} == 4'b0110) ? 1'b1 :
                ({digit[7]^digit[6], digit[5]^digit[4], digit[3]^digit[2], digit[1]^digit[0]} == 4'b0111) ? 1'b1 : 1'b0;


endmodule

is_div_3/testbench.v
`timescale 1ns/1ps

module testbench;
reg [7:0] digit;
wire OUT;

is_div_3 DUT (digit, OUT);
initial begin
        $dumpfile("out.vcd");
        $dumpvars(0, testbench);
        digit = 8'b11111111;
        #5;
        digit = 8'b01010010;
        #5;
        digit = 8'b01000000;
        #5;
        digit = 8'b00011111;
        #5;
        digit = 8'b00000000;
        #5;
        digit = 8'b00000011;
        #5;
        digit = 8'b00000110;
        #5;
        digit = 8'b11111100;
        #5;
        digit = 8'b00011000;
        #5;
        digit = 8'b00110110;
        #5;
        digit = 8'b10001100;
        #5;
        $finish;
end
endmodule

is_div_3/out.vcd
$date
	Sun Jul  7 14:26:30 2024
$end
$version
	Icarus Verilog
$end
$timescale
	1ps
$end
$scope module testbench $end
$var wire 1 ! OUT $end
$var reg 8 " digit [7:0] $end
$scope module DUT $end
$var wire 8 # digit [7:0] $end
$var wire 1 ! OUT $end
$upscope $end
$upscope $end
$enddefinitions $end
#0
$dumpvars
b11111111 #
b11111111 "
1!
$end
#5000
0!
b1010010 "
b1010010 #
#10000
b1000000 "
b1000000 #
#15000
b11111 "
b11111 #
#20000
1!
b0 "
b0 #
#25000
b11 "
b11 #
#30000
b110 "
b110 #
#35000
b11111100 "
b11111100 #
#40000
1!
b11000 "
b11000 #
#45000
b110110 "
b110110 #
#50000
0!
b10001100 "
b10001100 #
