Parameterized_modules/Axi4/Axi_stream.v
module Axi4_stream
#(
        parameter DATA_W = 8,
        parameter LEN = 4
)
(
        input  wire                      clk,
        input  wire                      reset,
        input  wire [DATA_W     - 1 : 0] s_tdata,
        input  wire                      s_tvalid,
        input  wire                      s_tlast,
        input  wire [DATA_W*LEN - 1 : 0] marker,
        input  wire                      m_tready,
        output wire                      s_tready,
        output wire [DATA_W     - 1 : 0] m_tdata,
        output wire                      m_tvalid,
        output wire                      m_tlast
);

wire handshake;
wire [DATA_W - 1 : 0] marker_sep [LEN : 1];


reg [DATA_W  + 1 : 0] buff [LEN : 0];
reg [$clog2(LEN) : 0] counter;


assign s_tready      = m_tready;
assign m_tvalid      = ~reset & buff[0][0] | buff[LEN][0];
assign m_tlast       = buff[LEN][1];
assign handshake     = m_tvalid & m_tready;


genvar i;

generate for (i = LEN; i >= 1; i = i - 1)
begin: loop_1
        assign marker_sep[i] = marker[i*DATA_W - 1 : (i - 1)* DATA_W];
end
endgenerate


genvar g;

generate for (g = 0; g <= LEN; g = g + 1) begin: loop_2
        always @(posedge clk)
                if (g == 0)
                        buff[0] <= {s_tdata, s_tlast, s_tvalid};
                else 
                        buff[g] <= buff[g - 1];

end
endgenerate

always @(posedge clk) begin
        if (reset) begin
                counter <= LEN;
        end
        if (buff[LEN][1]) begin
                counter <= LEN;
        end
        if (handshake) begin
                if (counter != 0) begin
                        counter <= counter - 1'b1;
                end
        end
end

assign m_tdata = (handshake && counter != 0) ? marker_sep[counter] : buff[LEN][DATA_W + 1 : 2];

endmodule

Parameterized_modules/Axi4/testbench.v
`timescale 1ns/1ps


module testbench;
reg                      clk;
reg                      reset;
reg [8          - 1 : 0] s_tdata;
reg                      s_tvalid;
reg                      s_tlast;
reg [32         - 1 : 0] marker;
reg                      m_tready;


initial begin
        clk = 0;
        reset = 1;
        marker = 32'hFFFFFFFF;
        m_tready = 1;
        s_tlast = 0;
        s_tvalid = 0;
end
always #1 clk = ~clk;


Axi4_stream #(.DATA_W(8), .LEN(4)) DUT (
        .clk(clk),
        .reset(reset),
        .s_tdata(s_tdata),
        .s_tvalid(s_tvalid),
        .s_tlast(s_tlast),
        .marker(marker),
        .m_tready(m_tready)
);





initial begin
        $dumpfile("out.vcd");
        $dumpvars(0, testbench);
        #11;
        reset = 0;
        #10;
        s_tvalid = 1;
        s_tdata = $random;
        #2;
        s_tdata = $random;
        #2;
        s_tdata = $random;
        #2;
        s_tdata = $random;
        #2;
        s_tdata = $random;
        #2;
        s_tdata = $random;
        #2;
        s_tdata = $random;
        #2;
        m_tready = 0;
        #2;
        #2;
        #2;
        m_tready = 1;
        s_tdata = $random;
        #2;
        s_tdata = $random;
        #2;
        s_tdata = $random;
        #2;
        s_tdata = $random;
        #2;
        s_tdata = $random;
        #2;
        s_tdata = $random;
        #2;
        s_tdata = $random;
        s_tlast = 1;
        #2;
        s_tvalid = 0;   
        s_tlast = 0;
        #1000;

        $finish;
end






endmodule

Parameterized_modules/Axi4/out.vcd
$date
	Tue Oct 15 17:48:32 2024
$end
$version
	Icarus Verilog
$end
$timescale
	1ps
$end
$scope module testbench $end
$var reg 1 ! clk $end
$var reg 1 " m_tready $end
$var reg 32 # marker [31:0] $end
$var reg 1 $ reset $end
$var reg 8 % s_tdata [7:0] $end
$var reg 1 & s_tlast $end
$var reg 1 ' s_tvalid $end
$scope module DUT $end
$var wire 1 ! clk $end
$var wire 1 ( handshake $end
$var wire 1 " m_tready $end
$var wire 1 ) m_tvalid $end
$var wire 32 * marker [31:0] $end
$var wire 1 $ reset $end
$var wire 8 + s_tdata [7:0] $end
$var wire 1 & s_tlast $end
$var wire 1 , s_tready $end
$var wire 1 ' s_tvalid $end
$var wire 1 - m_tlast $end
$var wire 8 . m_tdata [7:0] $end
$var reg 3 / counter [2:0] $end
$scope begin loop_1[1] $end
$upscope $end
$scope begin loop_1[2] $end
$upscope $end
$scope begin loop_1[3] $end
$upscope $end
$scope begin loop_1[4] $end
$upscope $end
$scope begin loop_2[0] $end
$upscope $end
$scope begin loop_2[1] $end
$upscope $end
$scope begin loop_2[2] $end
$upscope $end
$scope begin loop_2[3] $end
$upscope $end
$scope begin loop_2[4] $end
$upscope $end
$upscope $end
$upscope $end
$enddefinitions $end
#0
$dumpvars
bx /
bx .
x-
1,
bx +
b11111111111111111111111111111111 *
x)
x(
0'
0&
bx %
1$
b11111111111111111111111111111111 #
1"
0!
$end
#1000
b100 /
1!
#2000
0!
#3000
1!
#4000
0!
#5000
1!
#6000
0!
#7000
1!
#8000
0!
#9000
0(
0)
0-
1!
#10000
0!
#11000
1!
0$
#12000
0!
#13000
1!
#14000
0!
#15000
1!
#16000
0!
#17000
1!
#18000
0!
#19000
1!
#20000
0!
#21000
b11111111 .
1(
1)
1!
b100100 %
b100100 +
1'
#22000
0!
#23000
b11 /
1!
b10000001 %
b10000001 +
#24000
0!
#25000
b10 /
1!
b1001 %
b1001 +
#26000
0!
#27000
b1 /
1!
b1100011 %
b1100011 +
#28000
0!
#29000
b100100 .
b0 /
1!
b1101 %
b1101 +
#30000
0!
#31000
b10000001 .
1!
b10001101 %
b10001101 +
#32000
0!
#33000
b1001 .
1!
b1100101 %
b1100101 +
#34000
0!
#35000
b1100011 .
0(
1!
0,
0"
#36000
0!
#37000
b1101 .
1!
#38000
0!
#39000
b10001101 .
1!
#40000
0!
#41000
b1100101 .
1(
1!
b10010 %
b10010 +
1,
1"
#42000
0!
#43000
1!
b1 %
b1 +
#44000
0!
#45000
1!
b1101 %
b1101 +
#46000
0!
#47000
1!
b1110110 %
b1110110 +
#48000
0!
#49000
b10010 .
1!
b111101 %
b111101 +
#50000
0!
#51000
b1 .
1!
b11101101 %
b11101101 +
#52000
0!
#53000
b1101 .
1!
1&
b10001100 %
b10001100 +
#54000
0!
#55000
b1110110 .
1!
0&
0'
#56000
0!
#57000
b111101 .
1!
#58000
0!
#59000
b11101101 .
1!
#60000
0!
#61000
b10001100 .
1-
1!
#62000
0!
#63000
0(
b10001100 .
0)
0-
b100 /
1!
