Parameterized_modules/is_div_3/is_div_3.v
module is_div_3
#(
        parameter SIZE = 8
)
(
        input  wire [SIZE - 1:0] digit,
        output wire out
);


function automatic isdiv3;
        input [SIZE - 1:0] digit_in;
        reg   [$clog2(SIZE):0] counter_even;
        reg   [$clog2(SIZE):0] counter_odd;
        integer i, g;
        begin
                counter_even = 0;
                counter_odd = 0;

                for (i = 0; i < SIZE; i = i + 2) begin
                        counter_even = (digit_in[i]) ? counter_even + 1 : counter_even;
                end
                for (g = 1; g < SIZE; g = g + 2) begin
                        counter_odd = (digit_in[g]) ? counter_odd + 1 : counter_odd;
                end
                if (counter_even > counter_odd) begin
                        if (((counter_even - counter_odd) == 3)) begin
                                isdiv3 = 1;
                        end
                        else if ((counter_even - counter_odd) == 1 || 2) begin
                                isdiv3 = 0;
                        end
                        else begin
                                isdiv3 = isdiv3(counter_even - counter_odd);
                        end
                end
                else if (counter_even < counter_odd) begin
                        if (((counter_odd - counter_even) == 3)) begin
                                isdiv3 = 1;
                        end
                        else if ((counter_odd - counter_even) == 1 || 2) begin
                                isdiv3 = 0;
                        end
                        else begin
                                isdiv3 = isdiv3(counter_odd - counter_even);
                        end
                end
                else begin
                        isdiv3 = 1;
                end
                
        end
endfunction

assign out = isdiv3(digit);

endmodule

Parameterized_modules/is_div_3/testbench.v
`timescale 1ns/1ps

module testbench;
reg [7:0] digit;
wire OUT;

is_div_3 #(.SIZE(8)) DUT (
        .digit(digit),
        .out(out)
 );

integer i;
initial begin
        $dumpfile("out.vcd");
        $dumpvars(0, testbench);
        digit = 0;
        repeat (255) begin
                digit = digit + 1;
                #1;
        end
        $finish;
end
endmodule

Parameterized_modules/is_div_3/out.vcd
$date
	Tue Jul 16 11:09:26 2024
$end
$version
	Icarus Verilog
$end
$timescale
	1ps
$end
$scope module testbench $end
$var wire 1 ! out $end
$var reg 8 " digit [7:0] $end
$scope module DUT $end
$var wire 8 # digit [7:0] $end
$var wire 1 ! out $end
$scope function isdiv3 $end
$upscope $end
$upscope $end
$upscope $end
$enddefinitions $end
#0
$dumpvars
b1 #
b1 "
0!
$end
#1000
b10 "
b10 #
#2000
1!
b11 "
b11 #
#3000
0!
b100 "
b100 #
#4000
b101 "
b101 #
#5000
1!
b110 "
b110 #
#6000
0!
b111 "
b111 #
#7000
b1000 "
b1000 #
#8000
1!
b1001 "
b1001 #
#9000
0!
b1010 "
b1010 #
#10000
b1011 "
b1011 #
#11000
1!
b1100 "
b1100 #
#12000
0!
b1101 "
b1101 #
#13000
b1110 "
b1110 #
#14000
1!
b1111 "
b1111 #
#15000
0!
b10000 "
b10000 #
#16000
b10001 "
b10001 #
#17000
1!
b10010 "
b10010 #
#18000
0!
b10011 "
b10011 #
#19000
b10100 "
b10100 #
#20000
1!
b10101 "
b10101 #
#21000
0!
b10110 "
b10110 #
#22000
b10111 "
b10111 #
#23000
1!
b11000 "
b11000 #
#24000
0!
b11001 "
b11001 #
#25000
b11010 "
b11010 #
#26000
1!
b11011 "
b11011 #
#27000
0!
b11100 "
b11100 #
#28000
b11101 "
b11101 #
#29000
1!
b11110 "
b11110 #
#30000
0!
b11111 "
b11111 #
#31000
b100000 "
b100000 #
#32000
1!
b100001 "
b100001 #
#33000
0!
b100010 "
b100010 #
#34000
b100011 "
b100011 #
#35000
1!
b100100 "
b100100 #
#36000
0!
b100101 "
b100101 #
#37000
b100110 "
b100110 #
#38000
1!
b100111 "
b100111 #
#39000
0!
b101000 "
b101000 #
#40000
b101001 "
b101001 #
#41000
1!
b101010 "
b101010 #
#42000
0!
b101011 "
b101011 #
#43000
b101100 "
b101100 #
#44000
1!
b101101 "
b101101 #
#45000
0!
b101110 "
b101110 #
#46000
b101111 "
b101111 #
#47000
1!
b110000 "
b110000 #
#48000
0!
b110001 "
b110001 #
#49000
b110010 "
b110010 #
#50000
1!
b110011 "
b110011 #
#51000
0!
b110100 "
b110100 #
#52000
b110101 "
b110101 #
#53000
1!
b110110 "
b110110 #
#54000
0!
b110111 "
b110111 #
#55000
b111000 "
b111000 #
#56000
1!
b111001 "
b111001 #
#57000
0!
b111010 "
b111010 #
#58000
b111011 "
b111011 #
#59000
1!
b111100 "
b111100 #
#60000
0!
b111101 "
b111101 #
#61000
b111110 "
b111110 #
#62000
1!
b111111 "
b111111 #
#63000
0!
b1000000 "
b1000000 #
#64000
b1000001 "
b1000001 #
#65000
1!
b1000010 "
b1000010 #
#66000
0!
b1000011 "
b1000011 #
#67000
b1000100 "
b1000100 #
#68000
1!
b1000101 "
b1000101 #
#69000
0!
b1000110 "
b1000110 #
#70000
b1000111 "
b1000111 #
#71000
1!
b1001000 "
b1001000 #
#72000
0!
b1001001 "
b1001001 #
#73000
b1001010 "
b1001010 #
#74000
1!
b1001011 "
b1001011 #
#75000
0!
b1001100 "
b1001100 #
#76000
b1001101 "
b1001101 #
#77000
1!
b1001110 "
b1001110 #
#78000
0!
b1001111 "
b1001111 #
#79000
b1010000 "
b1010000 #
#80000
1!
b1010001 "
b1010001 #
#81000
0!
b1010010 "
b1010010 #
#82000
b1010011 "
b1010011 #
#83000
1!
b1010100 "
b1010100 #
#84000
0!
b1010101 "
b1010101 #
#85000
b1010110 "
b1010110 #
#86000
1!
b1010111 "
b1010111 #
#87000
0!
b1011000 "
b1011000 #
#88000
b1011001 "
b1011001 #
#89000
1!
b1011010 "
b1011010 #
#90000
0!
b1011011 "
b1011011 #
#91000
b1011100 "
b1011100 #
#92000
1!
b1011101 "
b1011101 #
#93000
0!
b1011110 "
b1011110 #
#94000
b1011111 "
b1011111 #
#95000
1!
b1100000 "
b1100000 #
#96000
0!
b1100001 "
b1100001 #
#97000
b1100010 "
b1100010 #
#98000
1!
b1100011 "
b1100011 #
#99000
0!
b1100100 "
b1100100 #
#100000
b1100101 "
b1100101 #
#101000
1!
b1100110 "
b1100110 #
#102000
0!
b1100111 "
b1100111 #
#103000
b1101000 "
b1101000 #
#104000
1!
b1101001 "
b1101001 #
#105000
0!
b1101010 "
b1101010 #
#106000
b1101011 "
b1101011 #
#107000
1!
b1101100 "
b1101100 #
#108000
0!
b1101101 "
b1101101 #
#109000
b1101110 "
b1101110 #
#110000
1!
b1101111 "
b1101111 #
#111000
0!
b1110000 "
b1110000 #
#112000
b1110001 "
b1110001 #
#113000
1!
b1110010 "
b1110010 #
#114000
0!
b1110011 "
b1110011 #
#115000
b1110100 "
b1110100 #
#116000
1!
b1110101 "
b1110101 #
#117000
0!
b1110110 "
b1110110 #
#118000
b1110111 "
b1110111 #
#119000
1!
b1111000 "
b1111000 #
#120000
0!
b1111001 "
b1111001 #
#121000
b1111010 "
b1111010 #
#122000
1!
b1111011 "
b1111011 #
#123000
0!
b1111100 "
b1111100 #
#124000
b1111101 "
b1111101 #
#125000
1!
b1111110 "
b1111110 #
#126000
0!
b1111111 "
b1111111 #
#127000
b10000000 "
b10000000 #
#128000
1!
b10000001 "
b10000001 #
#129000
0!
b10000010 "
b10000010 #
#130000
b10000011 "
b10000011 #
#131000
1!
b10000100 "
b10000100 #
#132000
0!
b10000101 "
b10000101 #
#133000
b10000110 "
b10000110 #
#134000
1!
b10000111 "
b10000111 #
#135000
0!
b10001000 "
b10001000 #
#136000
b10001001 "
b10001001 #
#137000
1!
b10001010 "
b10001010 #
#138000
0!
b10001011 "
b10001011 #
#139000
b10001100 "
b10001100 #
#140000
1!
b10001101 "
b10001101 #
#141000
0!
b10001110 "
b10001110 #
#142000
b10001111 "
b10001111 #
#143000
1!
b10010000 "
b10010000 #
#144000
0!
b10010001 "
b10010001 #
#145000
b10010010 "
b10010010 #
#146000
1!
b10010011 "
b10010011 #
#147000
0!
b10010100 "
b10010100 #
#148000
b10010101 "
b10010101 #
#149000
1!
b10010110 "
b10010110 #
#150000
0!
b10010111 "
b10010111 #
#151000
b10011000 "
b10011000 #
#152000
1!
b10011001 "
b10011001 #
#153000
0!
b10011010 "
b10011010 #
#154000
b10011011 "
b10011011 #
#155000
1!
b10011100 "
b10011100 #
#156000
0!
b10011101 "
b10011101 #
#157000
b10011110 "
b10011110 #
#158000
1!
b10011111 "
b10011111 #
#159000
0!
b10100000 "
b10100000 #
#160000
b10100001 "
b10100001 #
#161000
1!
b10100010 "
b10100010 #
#162000
0!
b10100011 "
b10100011 #
#163000
b10100100 "
b10100100 #
#164000
1!
b10100101 "
b10100101 #
#165000
0!
b10100110 "
b10100110 #
#166000
b10100111 "
b10100111 #
#167000
1!
b10101000 "
b10101000 #
#168000
0!
b10101001 "
b10101001 #
#169000
b10101010 "
b10101010 #
#170000
1!
b10101011 "
b10101011 #
#171000
0!
b10101100 "
b10101100 #
#172000
b10101101 "
b10101101 #
#173000
1!
b10101110 "
b10101110 #
#174000
0!
b10101111 "
b10101111 #
#175000
b10110000 "
b10110000 #
#176000
1!
b10110001 "
b10110001 #
#177000
0!
b10110010 "
b10110010 #
#178000
b10110011 "
b10110011 #
#179000
1!
b10110100 "
b10110100 #
#180000
0!
b10110101 "
b10110101 #
#181000
b10110110 "
b10110110 #
#182000
1!
b10110111 "
b10110111 #
#183000
0!
b10111000 "
b10111000 #
#184000
b10111001 "
b10111001 #
#185000
1!
b10111010 "
b10111010 #
#186000
0!
b10111011 "
b10111011 #
#187000
b10111100 "
b10111100 #
#188000
1!
b10111101 "
b10111101 #
#189000
0!
b10111110 "
b10111110 #
#190000
b10111111 "
b10111111 #
#191000
1!
b11000000 "
b11000000 #
#192000
0!
b11000001 "
b11000001 #
#193000
b11000010 "
b11000010 #
#194000
1!
b11000011 "
b11000011 #
#195000
0!
b11000100 "
b11000100 #
#196000
b11000101 "
b11000101 #
#197000
1!
b11000110 "
b11000110 #
#198000
0!
b11000111 "
b11000111 #
#199000
b11001000 "
b11001000 #
#200000
1!
b11001001 "
b11001001 #
#201000
0!
b11001010 "
b11001010 #
#202000
b11001011 "
b11001011 #
#203000
1!
b11001100 "
b11001100 #
#204000
0!
b11001101 "
b11001101 #
#205000
b11001110 "
b11001110 #
#206000
1!
b11001111 "
b11001111 #
#207000
0!
b11010000 "
b11010000 #
#208000
b11010001 "
b11010001 #
#209000
1!
b11010010 "
b11010010 #
#210000
0!
b11010011 "
b11010011 #
#211000
b11010100 "
b11010100 #
#212000
1!
b11010101 "
b11010101 #
#213000
0!
b11010110 "
b11010110 #
#214000
b11010111 "
b11010111 #
#215000
1!
b11011000 "
b11011000 #
#216000
0!
b11011001 "
b11011001 #
#217000
b11011010 "
b11011010 #
#218000
1!
b11011011 "
b11011011 #
#219000
0!
b11011100 "
b11011100 #
#220000
b11011101 "
b11011101 #
#221000
1!
b11011110 "
b11011110 #
#222000
0!
b11011111 "
b11011111 #
#223000
b11100000 "
b11100000 #
#224000
1!
b11100001 "
b11100001 #
#225000
0!
b11100010 "
b11100010 #
#226000
b11100011 "
b11100011 #
#227000
1!
b11100100 "
b11100100 #
#228000
0!
b11100101 "
b11100101 #
#229000
b11100110 "
b11100110 #
#230000
1!
b11100111 "
b11100111 #
#231000
0!
b11101000 "
b11101000 #
#232000
b11101001 "
b11101001 #
#233000
1!
b11101010 "
b11101010 #
#234000
0!
b11101011 "
b11101011 #
#235000
b11101100 "
b11101100 #
#236000
1!
b11101101 "
b11101101 #
#237000
0!
b11101110 "
b11101110 #
#238000
b11101111 "
b11101111 #
#239000
1!
b11110000 "
b11110000 #
#240000
0!
b11110001 "
b11110001 #
#241000
b11110010 "
b11110010 #
#242000
1!
b11110011 "
b11110011 #
#243000
0!
b11110100 "
b11110100 #
#244000
b11110101 "
b11110101 #
#245000
1!
b11110110 "
b11110110 #
#246000
0!
b11110111 "
b11110111 #
#247000
b11111000 "
b11111000 #
#248000
1!
b11111001 "
b11111001 #
#249000
0!
b11111010 "
b11111010 #
#250000
b11111011 "
b11111011 #
#251000
1!
b11111100 "
b11111100 #
#252000
0!
b11111101 "
b11111101 #
#253000
b11111110 "
b11111110 #
#254000
1!
b11111111 "
b11111111 #
