Parameterized_modules/CSA/carry_save_adder.v
module CSA
#(
        parameter DATA_W = 8
)
(
        input  wire [DATA_W - 1 : 0] op_A,
        input  wire [DATA_W - 1 : 0] op_B,
        input  wire [DATA_W - 1 : 0] op_C,
        output wire [DATA_W + 1 : 0] res
);

wire [DATA_W - 1 : 0] ps;
wire [DATA_W - 1 : 0] pc;


genvar i;
generate for (i = 0; i < DATA_W; i = i + 1)
begin: loop
        assign ps[i] = op_A[i] ^ op_B[i] ^ op_C[i];
        assign pc[i] = (op_A[i] & op_B[i]) | (op_A[i] & op_C[i]) | (op_B[i] & op_C[i]);
end     
endgenerate

assign res = ps + (pc << 1);


endmodule

Parameterized_modules/CSA/testbench.v
`timescale 1ns/1ps


module testbench;
reg [7:0] op_A;
reg [7:0] op_B;
reg [7:0] op_C;
wire [9:0] res;

CSA #(.DATA_W(8)) DUT
(
        .op_A(op_A),
        .op_B(op_B),
        .op_C(op_C),
        .res(res)
);

wire [9:0] res_eth; 

assign res_eth = op_A+op_B+op_C;

initial
begin
        $dumpfile("out.vcd");
        $dumpvars(0, testbench);

        
        op_A = 8'b11111111;
        op_B = 8'b11111111;
        op_C = 8'b11111111;
        if (res != res_eth)
                begin
                        $display("ERROR");
                        $stop();
                end
                #2;

        repeat (1000)
        begin
                op_A = $random;
                op_B = $random;
                op_C = $random;
                #2;
                if (res != res_eth)
                begin
                        $display("ERROR");
                        $stop();
                end
        end

        $finish;
end
endmodule

Parameterized_modules/CSA/out.vcd
$date
	Mon Aug  5 14:20:13 2024
$end
$version
	Icarus Verilog
$end
$timescale
	1ps
$end
$scope module testbench $end
$var wire 10 ! res_eth [9:0] $end
$var wire 10 " res [9:0] $end
$var reg 8 # op_A [7:0] $end
$var reg 8 $ op_B [7:0] $end
$var reg 8 % op_C [7:0] $end
$scope module DUT $end
$var wire 8 & op_A [7:0] $end
$var wire 8 ' op_B [7:0] $end
$var wire 8 ( op_C [7:0] $end
$var wire 10 ) res [9:0] $end
$var wire 8 * ps [7:0] $end
$var wire 8 + pc [7:0] $end
$scope begin loop[0] $end
$upscope $end
$scope begin loop[1] $end
$upscope $end
$scope begin loop[2] $end
$upscope $end
$scope begin loop[3] $end
$upscope $end
$scope begin loop[4] $end
$upscope $end
$scope begin loop[5] $end
$upscope $end
$scope begin loop[6] $end
$upscope $end
$scope begin loop[7] $end
$upscope $end
$upscope $end
$upscope $end
$enddefinitions $end
#0
$dumpvars
b11111111 +
b11111111 *
b1011111101 )
b11111111 (
b11111111 '
b11111111 &
b11111111 %
b11111111 $
b11111111 #
b1011111101 "
b1011111101 !
$end
#2000
b1 +
b10101110 "
b10101110 )
b10101100 *
b1001 %
b1001 (
b10000001 $
b10000001 '
b10101110 !
b100100 #
b100100 &
#4000
b1101 +
b11111101 "
b11111101 )
b11100011 *
b10001101 %
b10001101 (
b1101 $
b1101 '
b11111101 !
b1100011 #
b1100011 &
#6000
b1 +
b1111000 "
b1111000 )
b1110110 *
b1 %
b1 (
b10010 $
b10010 '
b1111000 !
b1100101 #
b1100101 &
#8000
b111101 +
b11000000 "
b11000000 )
b1000110 *
b111101 %
b111101 (
b1110110 $
b1110110 '
b11000000 !
b1101 #
b1101 &
#10000
b11101101 +
b1001110010 "
b1001110010 )
b10011000 *
b11111001 %
b11111001 (
b10001100 $
b10001100 '
b1001110010 !
b11101101 #
b11101101 &
#12000
b11000110 +
b1000110101 "
b1000110101 )
b10101001 *
b10101010 %
b10101010 (
b11000101 $
b11000101 '
b1000110101 !
b11000110 #
b11000110 &
#14000
b1110111 +
b101101110 "
b101101110 )
b10000000 *
b10010 %
b10010 (
b1110111 $
b1110111 '
b101101110 !
b11100101 #
b11100101 &
#16000
b11001110 +
b1001001111 "
b1001001111 )
b10110011 *
b11001110 %
b11001110 (
b11110010 $
b11110010 '
b1001001111 !
b10001111 #
b10001111 &
#18000
b11001100 +
b1000001001 "
b1000001001 )
b1110001 *
b1011100 %
b1011100 (
b11000101 $
b11000101 '
b1000001001 !
b11101000 #
b11101000 &
#20000
b101101 +
b101001111 "
b101001111 )
b11110101 *
b1100101 %
b1100101 (
b101101 $
b101101 '
b101001111 !
b10111101 #
b10111101 &
#22000
b10 +
b11101101 "
b11101101 )
b11101001 *
b10000000 %
b10000000 (
b1010 $
b1010 '
b11101101 !
b1100011 #
b1100011 &
#24000
b10101000 +
b101100111 "
b101100111 )
b10111 *
b10011101 %
b10011101 (
b10101010 $
b10101010 '
b101100111 !
b100000 #
b100000 &
#26000
b10111 +
b10110110 "
b10110110 )
b10001000 *
b1101 %
b1101 (
b10011 $
b10011 '
b10110110 !
b10010110 #
b10010110 &
#28000
b1010011 +
b110010011 "
b110010011 )
b11101101 *
b11010101 %
b11010101 (
b1101011 $
b1101011 '
b110010011 !
b1010011 #
b1010011 &
#30000
b1110 +
b11001101 "
b11001101 )
b10110001 *
b11101 %
b11101 (
b10101110 $
b10101110 '
b11001101 !
b10 #
b10 &
#32000
b1011 +
b11111100 "
b11111100 )
b11100110 *
b1010 %
b1010 (
b100011 $
b100011 '
b11111100 !
b11001111 #
b11001111 &
#34000
b11111010 +
b111111000 "
b111111000 )
b100 *
b11110010 %
b11110010 (
b111100 $
b111100 '
b111111000 !
b11001010 #
b11001010 &
#36000
b11001000 +
b110100011 "
b110100011 )
b10011 *
b11011000 %
b11011000 (
b1000001 $
b1000001 '
b110100011 !
b10001010 #
b10001010 &
#38000
b11101001 +
b111101100 "
b111101100 )
b11010 *
b11101011 %
b11101011 (
b10001001 $
b10001001 '
b111101100 !
b1111000 #
b1111000 &
#40000
b10100110 +
b1000101010 "
b1000101010 )
b11011110 *
b10101110 %
b10101110 (
b11000110 $
b11000110 '
b1000101010 !
b10110110 #
b10110110 &
#42000
b101010 +
b11110001 "
b11110001 )
b10011101 *
b1011 %
b1011 (
b101010 $
b101010 '
b11110001 !
b10111100 #
b10111100 &
#44000
b1000101 +
b101000101 "
b101000101 )
b10111011 *
b1001111 %
b1001111 (
b10000101 $
b10000101 '
b101000101 !
b1110001 #
b1110001 &
#46000
b111010 +
b11110011 "
b11110011 )
b1111111 *
b1111110 %
b1111110 (
b111010 $
b111010 '
b11110011 !
b111011 #
b111011 &
#48000
b11010001 +
b111011111 "
b111011111 )
b111101 *
b11011001 %
b11011001 (
b11110001 $
b11110001 '
b111011111 !
b10101 #
b10101 &
#50000
b1001110 +
b101001101 "
b101001101 )
b10110001 *
b10011111 %
b10011111 (
b1001100 $
b1001100 '
b101001101 !
b1100010 #
b1100010 &
#52000
b10111111 +
b1000111110 "
b1000111110 )
b11000000 *
b10110111 %
b10110111 (
b11111000 $
b11111000 '
b1000111110 !
b10001111 #
b10001111 &
#54000
b1011111 +
b101010110 "
b101010110 )
b10011000 *
b1011011 %
b1011011 (
b1011100 $
b1011100 '
b101010110 !
b10011111 #
b10011111 &
#56000
b11001001 +
b110100010 "
b110100010 )
b10000 *
b11010000 %
b11010000 (
b1001001 $
b1001001 '
b110100010 !
b10001001 #
b10001001 &
#58000
b110111110 "
b110111110 )
b11010111 +
b10010110 %
b10010110 (
b1010001 $
b1010001 '
b110111110 !
b11010111 #
b11010111 &
#60000
b11001000 +
b110010110 "
b110010110 )
b110 *
b11001000 %
b11001000 (
b11000010 $
b11000010 '
b110010110 !
b1100 #
b1100 &
#62000
b110111 +
b11000110 "
b11000110 )
b1011000 *
b10010 %
b10010 (
b111101 $
b111101 '
b11000110 !
b1110111 #
b1110111 &
#64000
b1111101 +
b100100100 "
b100100100 )
b101010 *
b111001 %
b111001 (
b1101101 $
b1101101 '
b100100100 !
b1111110 #
b1111110 &
#66000
b10010111 +
b101110111 "
b101110111 )
b1001001 *
b10000101 %
b10000101 (
b11010011 $
b11010011 '
b101110111 !
b11111 #
b11111 &
#68000
b1011001 +
b100011100 "
b100011100 )
b1101010 *
b1001001 %
b1001001 (
b1011011 $
b1011011 '
b100011100 !
b1111000 #
b1111000 &
#70000
b111010 +
b11000001 "
b11000001 )
b1001101 *
b1011000 %
b1011000 (
b101010 $
b101010 '
b11000001 !
b111111 #
b111111 &
#72000
b10001110 +
b110110000 "
b110110000 )
b10010100 *
b10011100 %
b10011100 (
b10001110 $
b10001110 '
b110110000 !
b10000110 #
b10000110 &
#74000
b1110010 +
b110010011 "
b110010011 )
b10101111 *
b1110011 %
b1110011 (
b100110 $
b100110 '
b110010011 !
b11111010 #
b11111010 &
#76000
b10100011 +
b110000101 "
b110000101 )
b111111 *
b10110011 %
b10110011 (
b101111 $
b101111 '
b110000101 !
b10100011 #
b10100011 &
#78000
b1010111 +
b110011010 "
b110011010 )
b11101100 *
b11110111 %
b11110111 (
b1000100 $
b1000100 '
b110011010 !
b1011111 #
b1011111 &
#80000
b11001010 +
b1000001011 "
b1000001011 )
b1110111 *
b1011010 %
b1011010 (
b11100110 $
b11100110 '
b1000001011 !
b11001011 #
b11001011 &
#82000
b11101001 +
b111110000 "
b111110000 )
b11110 *
b11011010 %
b11011010 (
b11101101 $
b11101101 '
b111110000 !
b101001 #
b101001 &
#84000
b11110101 +
b111111001 "
b111111001 )
b1111 *
b11011111 %
b11011111 (
b10110101 $
b10110101 '
b111111001 !
b1100101 #
b1100101 &
#86000
b1010000 +
b110001101 "
b110001101 )
b11101101 *
b11010000 %
b11010000 (
b1000100 $
b1000100 '
b110001101 !
b1111001 #
b1111001 &
#88000
b101010 +
b11100011 "
b11100011 )
b10001111 *
b1110 %
b1110 (
b10101011 $
b10101011 '
b11100011 !
b101010 #
b101010 &
#90000
b11011100 +
b1001110011 "
b1001110011 )
b10111011 *
b11111101 %
b11111101 (
b10011010 $
b10011010 '
b1001110011 !
b11011100 #
b11011100 &
#92000
b1000110 +
b101100111 "
b101100111 )
b11011011 *
b1001110 %
b1001110 (
b1010110 $
b1010110 '
b101100111 !
b11000011 #
b11000011 &
#94000
b100100111 "
b100100111 )
b100110 +
b10110110 %
b10110110 (
b1010 $
b1010 '
b100100111 !
b1100111 #
b1100111 &
#96000
b111000 +
b101101001 "
b101101001 )
b11111001 *
b10111000 %
b10111000 (
b1111001 $
b1111001 '
b101101001 !
b111000 #
b111000 &
#98000
b10010100 +
b100101011 "
b100101011 )
b11 *
b100 %
b100 (
b10010011 $
b10010011 '
b100101011 !
b10010100 #
b10010100 &
#100000
b1011001 +
b110000001 "
b110000001 )
b11001111 *
b1001101 %
b1001101 (
b11011011 $
b11011011 '
b110000001 !
b1011001 #
b1011001 &
#102000
b1111101 +
b110111100 "
b110111100 )
b11000010 *
b1110110 %
b1110110 (
b1101101 $
b1101101 '
b110111100 !
b11011001 #
b11011001 &
#104000
b10010110 +
b1000010101 "
b1000010101 )
b11101001 *
b10010101 %
b10010101 (
b10110110 $
b10110110 '
b1000010101 !
b11001010 #
b11001010 &
#106000
b1000110 +
b101000001 "
b101000001 )
b10110101 *
b11110111 %
b11110111 (
b100 $
b100 '
b101000001 !
b1000110 #
b1000110 &
#108000
b10101000 +
b110100101 "
b110100101 )
b1010101 *
b10001000 %
b10001000 (
b10110100 $
b10110100 '
b110100101 !
b1101001 #
b1101001 &
#110000
b101101 +
b100011100 "
b100011100 )
b11000010 *
b11000111 %
b11000111 (
b101101 $
b101101 '
b100011100 !
b101000 #
b101000 &
#112000
b1100 +
b1010010 "
b1010010 )
b111010 *
b11100 %
b11100 (
b1000 $
b1000 '
b1010010 !
b101110 #
b101110 &
#114000
b111101 +
b101000010 "
b101000010 )
b11001000 *
b101001 $
b101001 '
b101000010 !
b11111101 #
b11111101 &
#116000
b10011110 +
b110011101 "
b110011101 )
b1100001 *
b111101 %
b111101 (
b11011010 $
b11011010 '
b110011101 !
b10000110 #
b10000110 &
#118000
b1110010 +
b101001001 "
b101001001 )
b1100101 *
b1110011 %
b1110011 (
b1110000 $
b1110000 '
b101001001 !
b1100110 #
b1100110 &
#120000
b11111010 +
b1000010010 "
b1000010010 )
b11110 *
b11111010 %
b11111010 (
b1011110 $
b1011110 '
b1000010010 !
b10111010 #
b10111010 &
#122000
b10011001 +
b110101000 "
b110101000 )
b1110110 *
b10111001 %
b10111001 (
b11010 $
b11010 '
b110101000 !
b11010101 #
b11010101 &
#124000
b10010110 +
b110001101 "
b110001101 )
b1100001 *
b11000000 %
b11000000 (
b10010110 $
b10010110 '
b110001101 !
b110111 #
b110111 &
#126000
b110110 +
b101011001 "
b101011001 )
b11101101 *
b1111101 %
b1111101 (
b10110110 $
b10110110 '
b101011001 !
b100110 #
b100110 &
#128000
b11011100 +
b111011010 "
b111011010 )
b100010 *
b1111000 %
b1111000 (
b10000110 $
b10000110 '
b111011010 !
b11011100 #
b11011100 &
#130000
b11011111 +
b1000101000 "
b1000101000 )
b1101010 *
b11001111 %
b11001111 (
b11011011 $
b11011011 '
b1000101000 !
b1111110 #
b1111110 &
#132000
b1111001 +
b111010100 "
b111010100 )
b11100010 *
b1100001 %
b1100001 (
b11111010 $
b11111010 '
b111010100 !
b1111001 #
b1111001 &
#134000
b10000111 +
b100111110 "
b100111110 )
b110000 *
b10000110 %
b10000110 (
b10100001 $
b10100001 '
b100111110 !
b10111 #
b10111 &
#136000
b1110101 +
b101111010 "
b101111010 )
b10010000 *
b110101 %
b110101 (
b11110101 $
b11110101 '
b101111010 !
b1010000 #
b1010000 &
#138000
b11000001 +
b110101111 "
b110101111 )
b101101 *
b11000101 %
b11000101 (
b11000001 $
b11000001 '
b110101111 !
b101001 #
b101001 &
#140000
b1011011 +
b101010110 "
b101010110 )
b10100000 *
b1110011 %
b1110011 (
b1001011 $
b1001011 '
b101010110 !
b10011000 #
b10011000 &
#142000
b11001110 +
b111000100 "
b111000100 )
b101000 *
b1001110 %
b1001110 (
b10001010 $
b10001010 '
b111000100 !
b11101100 #
b11101100 &
#144000
b10101001 +
b111110010 "
b111110010 )
b10100000 *
b10100001 %
b10100001 (
b10101001 $
b10101001 '
b111110010 !
b10101000 #
b10101000 &
#146000
b10001110 +
b110010011 "
b110010011 )
b1110111 *
b10011111 %
b10011111 (
b11100110 $
b11100110 '
b110010011 !
b1110 #
b1110 &
#148000
b101010 +
b11100001 "
b11100001 )
b10001101 *
b10001101 %
b10001101 (
b101010 $
b101010 '
b11100001 !
b101010 #
b101010 &
#150000
b111000 +
b101001111 "
b101001111 )
b11011111 *
b1111001 %
b1111001 (
b111000 $
b111000 '
b101001111 !
b10011110 #
b10011110 &
#152000
b11001010 +
b110100101 "
b110100101 )
b10001 *
b10011 %
b10011 (
b11001010 $
b11001010 '
b110100101 !
b11001000 #
b11001000 &
#154000
b11100111 +
b111101000 "
b111101000 )
b11010 *
b10110110 %
b10110110 (
b11000111 $
b11000111 '
b111101000 !
b1101011 #
b1101011 &
#156000
b10111000 +
b1000110111 "
b1000110111 )
b11000111 *
b10111001 %
b10111001 (
b11000100 $
b11000100 '
b1000110111 !
b10111010 #
b10111010 &
#158000
b10110110 +
b111000101 "
b111000101 )
b1011001 *
b1111111 %
b1111111 (
b10110100 $
b10110100 '
b111000101 !
b10010010 #
b10010010 &
#160000
b11110010 +
b1001110010 "
b1001110010 )
b10001110 *
b11110010 %
b11110010 (
b11111010 $
b11111010 '
b1001110010 !
b10000110 #
b10000110 &
#162000
b10110100 +
b101110011 "
b101110011 )
b1011 *
b10000100 %
b10000100 (
b10111101 $
b10111101 '
b101110011 !
b110010 #
b110010 &
#164000
b11101000 +
b1001010111 "
b1001010111 )
b10000111 *
b10101001 %
b10101001 (
b11001010 $
b11001010 '
b1001010111 !
b11100100 #
b11100100 &
#166000
b10101011 +
b1000101010 "
b1000101010 )
b11010100 *
b11111011 %
b11111011 (
b10001110 $
b10001110 '
b1000101010 !
b10100001 #
b10100001 &
#168000
b11001011 +
b111000011 "
b111000011 )
b101101 *
b11001001 %
b11001001 (
b11101111 $
b11101111 '
b111000011 !
b1011 #
b1011 &
#170000
b110111 +
b100111010 "
b100111010 )
b11001100 *
b10001111 %
b10001111 (
b1110101 $
b1110101 '
b100111010 !
b110110 #
b110110 &
#172000
b10101010 +
b110100001 "
b110100001 )
b1001101 *
b10101110 %
b10101110 (
b10001000 $
b10001000 '
b110100001 !
b1101011 #
b1101011 &
#174000
b10011010 +
b101010101 "
b101010101 )
b100001 *
b101000 %
b101000 (
b10010010 $
b10010010 '
b101010101 !
b10011011 #
b10011011 &
#176000
b1001011 +
b100111010 "
b100111010 )
b10100100 *
b11000010 %
b11000010 (
b1001011 $
b1001011 '
b100111010 !
b101101 #
b101101 &
#178000
b1100 +
b100010111 "
b100010111 )
b11111111 *
b11101100 %
b11101100 (
b1101 $
b1101 '
b100010111 !
b11110 #
b11110 &
#180000
b10010000 +
b101101111 "
b101101111 )
b1001111 *
b10000110 %
b10000110 (
b11010001 $
b11010001 '
b101101111 !
b11000 #
b11000 &
#182000
b1011001 +
b101010100 "
b101010100 )
b10100010 *
b11011000 %
b11011000 (
b111011 $
b111011 '
b101010100 !
b1000001 #
b1000001 &
#184000
b1010011 +
b100000100 "
b100000100 )
b1011110 *
b1011011 %
b1011011 (
b1010110 $
b1010110 '
b100000100 !
b1010011 #
b1010011 &
#186000
b1100010 +
b101011001 "
b101011001 )
b10010101 *
b1110011 %
b1110011 (
b100 $
b100 '
b101011001 !
b11100010 #
b11100010 &
#188000
b10011000 +
b110100010 "
b110100010 )
b1110010 *
b10111000 %
b10111000 (
b10010 $
b10010 '
b110100010 !
b11011000 #
b11011000 &
#190000
b10100001 +
b110111111 "
b110111111 )
b1111101 *
b10100001 %
b10100001 (
b11100101 $
b11100101 '
b110111111 !
b111001 #
b111001 &
#192000
b10001001 +
b101110100 "
b101110100 )
b1100010 *
b11001000 %
b11001000 (
b10000001 $
b10000001 '
b101110100 !
b101011 #
b101011 &
#194000
b100111 +
b11100111 "
b11100111 )
b10011001 *
b11111 %
b11111 (
b10100001 $
b10100001 '
b11100111 !
b100111 #
b100111 &
#196000
b10100 +
b11110010 "
b11110010 )
b11001010 *
b10010110 %
b10010110 (
b1011000 $
b1011000 '
b11110010 !
b100 #
b100 &
#198000
b10110 +
b10111100 "
b10111100 )
b10010000 *
b10010 $
b10010 '
b10111100 !
b10100 #
b10100 &
#200000
b11110101 +
b111110011 "
b111110011 )
b1001 *
b11101101 %
b11101101 (
b1010101 $
b1010101 '
b111110011 !
b10110001 #
b10110001 &
#202000
b10101101 +
b111001101 "
b111001101 )
b1110011 *
b10101101 %
b10101101 (
b11110101 $
b11110101 '
b111001101 !
b101011 #
b101011 &
#204000
b10100111 +
b101010010 "
b101010010 )
b100 *
b10100111 %
b10100111 (
b10000100 $
b10000100 '
b101010010 !
b100111 #
b100111 &
#206000
b11101001 +
b111101001 "
b111101001 )
b10111 *
b1001001 %
b1001001 (
b10111001 $
b10111001 '
b111101001 !
b11100111 #
b11100111 &
#208000
b11011001 +
b111110101 "
b111110101 )
b1000011 *
b1010001 %
b1010001 (
b11001001 $
b11001001 '
b111110101 !
b11011011 #
b11011011 &
#210000
b10101010 +
b111000101 "
b111000101 )
b1110001 *
b11111010 %
b11111010 (
b101010 $
b101010 '
b111000101 !
b10100001 #
b10100001 &
#212000
b1000101 +
b101000100 "
b101000100 )
b10111010 *
b1111100 %
b1111100 (
b10000011 $
b10000011 '
b101000100 !
b1000101 #
b1000101 &
#214000
b1111010 +
b111011000 "
b111011000 )
b11100100 *
b1101000 %
b1101000 (
b11111110 $
b11111110 '
b111011000 !
b1110010 #
b1110010 &
#216000
b11100110 +
b111100101 "
b111100101 )
b11001 *
b11110000 %
b11110000 (
b10000110 $
b10000110 '
b111100101 !
b1101111 #
b1101111 &
#218000
b101000 +
b10100000 "
b10100000 )
b1010000 *
b101000 %
b101000 (
b1000000 $
b1000000 '
b10100000 !
b111000 #
b111000 &
#220000
b11000100 +
b1001111011 "
b1001111011 )
b11110011 *
b11000000 %
b11000000 (
b11000101 $
b11000101 '
b1001111011 !
b11110110 #
b11110110 &
#222000
b110000 +
b101011101 "
b101011101 )
b11111101 *
b10110000 %
b10110000 (
b111001 $
b111001 '
b101011101 !
b1110100 #
b1110100 &
#224000
b101010 +
b11001000 "
b11001000 )
b1110100 *
b1100010 %
b1100010 (
b101010 $
b101010 '
b11001000 !
b111100 #
b111100 &
#226000
b10101 +
b100001101 "
b100001101 )
b11100011 *
b10111 %
b10111 (
b11100001 $
b11100001 '
b100001101 !
b10101 #
b10101 &
#228000
b11000011 +
b110010010 "
b110010010 )
b1100 *
b10000110 %
b10000110 (
b11001001 $
b11001001 '
b110010010 !
b1000011 #
b1000011 &
#230000
b10000101 +
b101110011 "
b101110011 )
b1101001 *
b10001101 %
b10001101 (
b11000001 $
b11000001 '
b101110011 !
b100101 #
b100101 &
#232000
b1110 +
b10001101 "
b10001101 )
b1110001 *
b101100 %
b101100 (
b111 $
b111 '
b10001101 !
b1011010 #
b1011010 &
#234000
b111001 +
b10111000 "
b10111000 )
b1000110 *
b111011 %
b111011 (
b1110001 $
b1110001 '
b10111000 !
b1100 #
b1100 &
#236000
b10110110 +
b1001001011 "
b1001001011 )
b11011111 *
b10011110 %
b10011110 (
b11110111 $
b11110111 '
b1001001011 !
b10110110 #
b10110110 &
#238000
b1010100 +
b11010001 "
b11010001 )
b101001 *
b100000 %
b100000 (
b1010101 $
b1010101 '
b11010001 !
b1011100 #
b1011100 &
#240000
b10110000 +
b111000110 "
b111000110 )
b1100110 *
b10110100 %
b10110100 (
b1110010 $
b1110010 '
b111000110 !
b10100000 #
b10100000 &
#242000
b1001101 +
b100110101 "
b100110101 )
b10011011 *
b1001011 %
b1001011 (
b1101 $
b1101 '
b100110101 !
b11011101 #
b11011101 &
#244000
b11111101 +
b1000010100 "
b1000010100 )
b11010 *
b11111101 %
b11111101 (
b10011110 $
b10011110 '
b1000010100 !
b1111001 #
b1111001 &
#246000
b1011 +
b100001101 "
b100001101 )
b11110111 *
b11 %
b11 (
b10001111 $
b10001111 '
b100001101 !
b1111011 #
b1111011 &
#248000
b10110001 +
b110110001 "
b110110001 )
b1001111 *
b10110001 %
b10110001 (
b11101 $
b11101 '
b110110001 !
b11100011 #
b11100011 &
#250000
b11000100 +
b110111001 "
b110111001 )
b110001 *
b11100000 %
b11100000 (
b10010101 $
b10010101 '
b110111001 !
b1000100 #
b1000100 &
#252000
b11111000 +
b1000110111 "
b1000110111 )
b1000111 *
b11111000 %
b11111000 (
b1010010 $
b1010010 '
b1000110111 !
b11101101 #
b11101101 &
#254000
b10000100 +
b101100011 "
b101100011 )
b1011011 *
b10000100 %
b10000100 (
b101100011 !
b10001101 #
b10001101 &
#256000
b101100010 "
b101100010 )
b1011010 *
b10010000 %
b10010000 (
b10001100 $
b10001100 '
b101100010 !
b1000110 #
b1000110 &
#258000
b110 +
b100000101 "
b100000101 )
b11111001 *
b10000100 %
b10000100 (
b1101010 $
b1101010 '
b100000101 !
b10111 #
b10111 &
#260000
b1101000 +
b110000110 "
b110000110 )
b10110110 *
b1100000 %
b1100000 (
b1111100 $
b1111100 '
b110000110 !
b10101010 #
b10101010 &
#262000
b111101011 "
b111101011 )
b10010111 *
b10101010 +
b10100110 %
b10100110 (
b10001011 $
b10001011 '
b111101011 !
b10111010 #
b10111010 &
#264000
b100010 +
b11111001 "
b11111001 )
b10110101 *
b10100010 %
b10100010 (
b110010 $
b110010 '
b11111001 !
b100101 #
b100101 &
#266000
b11101 +
b10011010 "
b10011010 )
b1100000 *
b111101 %
b111101 (
b10100 $
b10100 '
b10011010 !
b1001001 #
b1001001 &
#268000
b1001111 +
b11101110 "
b11101110 )
b1010000 *
b1000111 %
b1000111 (
b1011100 $
b1011100 '
b11101110 !
b1001011 #
b1001011 &
#270000
b10110100 +
b101110011 "
b101110011 )
b1011 *
b10110100 %
b10110100 (
b111001 $
b111001 '
b101110011 !
b10000110 #
b10000110 &
#272000
b10001100 +
b110001000 "
b110001000 )
b1110000 *
b10001100 %
b10001100 (
b101100 $
b101100 '
b110001000 !
b11010000 #
b11010000 &
#274000
b11 +
b10000010 "
b10000010 )
b1111100 *
b10001 %
b10001 (
b1101010 $
b1101010 '
b10000010 !
b111 #
b111 &
#276000
b1101011 +
b110100110 "
b110100110 )
b11010000 *
b1110011 %
b1110011 (
b1001011 $
b1001011 '
b110100110 !
b11101000 #
b11101000 &
#278000
b10100100 +
b110110011 "
b110110011 )
b1101011 *
b10100100 %
b10100100 (
b100011 $
b100011 '
b110110011 !
b11101100 #
b11101100 &
#280000
b11011001 +
b111100001 "
b111100001 )
b101111 *
b11011111 %
b11011111 (
b111001 $
b111001 '
b111100001 !
b11001001 #
b11001001 &
#282000
b11010101 +
b111011000 "
b111011000 )
b101110 *
b10011101 %
b10011101 (
b1100111 $
b1100111 '
b111011000 !
b11010100 #
b11010100 &
#284000
b10000000 +
b101111011 "
b101111011 )
b1111011 *
b1001001 %
b1001001 (
b10000010 $
b10000010 '
b101111011 !
b10110000 #
b10110000 &
#286000
b11000 +
b100010101 "
b100010101 )
b11100101 *
b11100 %
b11100 (
b100000 $
b100000 '
b100010101 !
b11011001 #
b11011001 &
#288000
b10100011 +
b110100000 "
b110100000 )
b1011010 *
b101010 %
b101010 (
b11100011 $
b11100011 '
b110100000 !
b10010011 #
b10010011 &
#290000
b1011000 +
b101011111 "
b101011111 )
b10101111 *
b111010 %
b111010 (
b1011101 $
b1011101 '
b101011111 !
b11001000 #
b11001000 &
#292000
b101001 +
b11101000 "
b11101000 )
b10010110 *
b111001 %
b111001 (
b101011 $
b101011 '
b11101000 !
b10000100 #
b10000100 &
#294000
b1010010 +
b10111101 "
b10111101 )
b11001 *
b1011001 %
b1011001 (
b1010010 $
b1010010 '
b10111101 !
b10010 #
b10010 &
#296000
b11010110 +
b111010101 "
b111010101 )
b101001 *
b10010111 %
b10010111 (
b1101110 $
b1101110 '
b111010101 !
b11010000 #
b11010000 &
#298000
b10111011 +
b1000111100 "
b1000111100 )
b11000110 *
b10111011 %
b10111011 (
b10100110 $
b10100110 '
b1000111100 !
b11011011 #
b11011011 &
#300000
b1001 +
b1111000 "
b1111000 )
b1100110 *
b1101001 %
b1101001 (
b1111 $
b1111 '
b1111000 !
b0 #
b0 &
#302000
b1001101 +
b100101010 "
b100101010 )
b10010000 *
b11000101 %
b11000101 (
b1011001 $
b1011001 '
b100101010 !
b1100 #
b1100 &
#304000
b11010001 +
b110110000 "
b110110000 )
b1110 *
b1010001 %
b1010001 (
b10010000 $
b10010000 '
b110110000 !
b11001111 #
b11001111 &
#306000
b1101011 +
b100101010 "
b100101010 )
b1010100 *
b1001010 %
b1001010 (
b1110111 $
b1110111 '
b100101010 !
b1101001 #
b1101001 &
#308000
b11011000 +
b1000110111 "
b1000110111 )
b10000111 *
b11000100 %
b11000100 (
b10011011 $
b10011011 '
b1000110111 !
b11011000 #
b11011000 &
#310000
b10110110 +
b111110101 "
b111110101 )
b10001001 *
b10000110 %
b10000110 (
b10110111 $
b10110111 '
b111110101 !
b10111000 #
b10111000 &
#312000
b110101 +
b101011100 "
b101011100 )
b11110010 *
b10110101 %
b10110101 (
b1110111 $
b1110111 '
b101011100 !
b110000 #
b110000 &
#314000
b1010110 +
b101010001 "
b101010001 )
b10100101 *
b1110110 %
b1110110 (
b111 $
b111 '
b101010001 !
b11010100 #
b11010100 &
#316000
b10001001 +
b101110101 "
b101110101 )
b1100011 *
b1 %
b1 (
b10001011 $
b10001011 '
b101110101 !
b11101001 #
b11101001 &
#318000
b11000010 +
b1000011101 "
b1000011101 )
b10011001 *
b11000010 %
b11000010 (
b10000000 $
b10000000 '
b1000011101 !
b11011011 #
b11011011 &
#320000
b10100101 +
b110100100 "
b110100100 )
b1011010 *
b10101111 %
b10101111 (
b110000 $
b110000 '
b110100100 !
b11000101 #
b11000101 &
#322000
b11101111 +
b111111110 "
b111111110 )
b100000 *
b11101001 %
b11101001 (
b10101111 $
b10101111 '
b111111110 !
b1100110 #
b1100110 &
#324000
b11101110 +
b111101101 "
b111101101 )
b10001 *
b11101111 %
b11101111 (
b110 $
b110 '
b111101101 !
b11111000 #
b11111000 &
#326000
b11100101 +
b1001100100 "
b1001100100 )
b10011010 *
b11101110 %
b11101110 (
b10010101 $
b10010101 '
b1001100100 !
b11100001 #
b11100001 &
#328000
b1100000 +
b101101101 "
b101101101 )
b10101101 *
b101000 %
b101000 (
b11100101 $
b11100101 '
b101101101 !
b1100000 #
b1100000 &
#330000
b1100001 +
b101101110 "
b101101110 )
b10101100 *
b11100001 %
b11100001 (
b101001 $
b101001 '
b101101110 !
b1100100 #
b1100100 &
#332000
b1100111 +
b101100110 "
b101100110 )
b10011000 *
b10000001 %
b10000001 (
b1101110 $
b1101110 '
b101100110 !
b1110111 #
b1110111 &
#334000
b11110000 +
b1000101101 "
b1000101101 )
b1001101 *
b11110000 %
b11110000 (
b1101000 $
b1101000 '
b1000101101 !
b11010101 #
b11010101 &
#336000
b10101011 +
b110101010 "
b110101010 )
b1010100 *
b11110001 %
b11110001 (
b1111 $
b1111 '
b110101010 !
b10101010 #
b10101010 &
#338000
b11101110 +
b111101101 "
b111101101 )
b10001 *
b11100010 %
b11100010 (
b10001110 $
b10001110 '
b111101101 !
b1111101 #
b1111101 &
#340000
b10101101 +
b111010100 "
b111010100 )
b1111010 *
b11101111 %
b11101111 (
b10101001 $
b10101001 '
b111010100 !
b111100 #
b111100 &
#342000
b1001011 +
b101010100 "
b101010100 )
b10111110 *
b1001010 %
b1001010 (
b10101111 $
b10101111 '
b101010100 !
b1011011 #
b1011011 &
#344000
b10011 +
b11011111 "
b11011111 )
b10111001 *
b10011 %
b10011 (
b10011 $
b10011 '
b11011111 !
b10111001 #
b10111001 &
#346000
b1110101 +
b101101101 "
b101101101 )
b10000011 *
b10110111 %
b10110111 (
b1010001 $
b1010001 '
b101101101 !
b1100101 #
b1100101 &
